{
  "metadata": {
    "nome": "Pratos Feitos Brasileiros - Informações Nutricionais Completas",
    "versao": "0.2.0",
    "gerado_em": "2026-06-25",
    "base_principal": "Baseado em tabelas TACO (UNICAMP), IBGE e literatura nutricional brasileira",
    "unidade_padrao": "porção média servida (gramas indicadas por prato)",
    "descricao": "Lista dos pratos feitos mais consumidos no Brasil com ingredientes e informações nutricionais por porção média",
    "aviso": "Valores estimados por porção média do prato. Ajustar por receita, restaurante e tamanho real da porção quando necessário."
  },
  "schema": {
    "energia_kcal": "kcal por porção de referência",
    "energia_kj": "kJ por porção de referência",
    "carboidratos_g": "g",
    "proteinas_g": "g",
    "gorduras_totais_g": "g",
    "gorduras_saturadas_g": "g",
    "gorduras_trans_g": "g",
    "fibra_alimentar_g": "g",
    "acucares_totais_g": "g",
    "sodio_mg": "mg",
    "alcool_g": "g; usado para bebidas alcoólicas",
    "calcio_mg": "mg",
    "ferro_mg": "mg",
    "potassio_mg": "mg",
    "vitamina_c_mg": "mg",
    "vitamina_A_mcg": "mcg",
    "vitamina_D_mcg": "mcg",
    "vitamina_E_mg": "mg",
    "vitamina_B12_mcg": "mcg",
    "folato_mcg": "mcg",
    "fosforo_mg": "mg",
    "magnesio_mg": "mg",
    "zinco_mg": "mg",
    "selenio_mcg": "mcg",
    "manganes_mg": "mg",
    "cobre_mg": "mg"
  },
  "alimentos": [
    {
      "id": "feijoada",
      "nome": "Feijoada",
      "categoria": "Pratos feitos brasileiros",
      "subcategoria": "Prato Nacional",
      "porcao_referencia": "500g",
      "nutrientes": {
        "energia_kcal": 620,
        "energia_kj": 2594.1,
        "carboidratos_g": 48,
        "proteinas_g": 42,
        "gorduras_totais_g": 26,
        "gorduras_saturadas_g": 9,
        "gorduras_trans_g": 0.3,
        "fibra_alimentar_g": 14,
        "acucares_totais_g": 3,
        "sodio_mg": 1420,
        "colesterol_mg": null,
        "alcool_g": 0,
        "calcio_mg": 90,
        "ferro_mg": 6.8,
        "potassio_mg": 820,
        "vitamina_c_mg": 4,
        "vitamina_A_mcg": 18,
        "vitamina_D_mcg": 0.5,
        "vitamina_E_mg": 1.2,
        "vitamina_B12_mcg": 1.8,
        "folato_mcg": 180,
        "fosforo_mg": 420,
        "magnesio_mg": 75,
        "zinco_mg": 5.2,
        "selenio_mcg": 22,
        "manganes_mg": 0.9,
        "cobre_mg": 0.4
      },
      "fonte": "Baseado em tabelas TACO (UNICAMP), IBGE e literatura nutricional brasileira",
      "observacoes": "Prato tradicional brasileiro com feijão preto e carnes variadas",
      "tags": [
        "prato feito",
        "preparação brasileira",
        "Prato Nacional",
        "Feijão preto cozido",
        "Calabresa",
        "Carne seca",
        "Paio",
        "Toucinho defumado",
        "Costelinha de porco",
        "Alho",
        "Cebola",
        "Folha de louro",
        "Azeite"
      ],
      "ingredientes": [
        {
          "nome": "Feijão preto cozido",
          "quantidade_g": 150
        },
        {
          "nome": "Calabresa",
          "quantidade_g": 60
        },
        {
          "nome": "Carne seca",
          "quantidade_g": 60
        },
        {
          "nome": "Paio",
          "quantidade_g": 40
        },
        {
          "nome": "Toucinho defumado",
          "quantidade_g": 30
        },
        {
          "nome": "Costelinha de porco",
          "quantidade_g": 60
        },
        {
          "nome": "Alho",
          "quantidade_g": 10
        },
        {
          "nome": "Cebola",
          "quantidade_g": 30
        },
        {
          "nome": "Folha de louro",
          "quantidade_g": 1
        },
        {
          "nome": "Azeite",
          "quantidade_g": 10
        }
      ]
    },
    {
      "id": "strogonoff_de_frango",
      "nome": "Strogonoff de Frango",
      "categoria": "Pratos feitos brasileiros",
      "subcategoria": "Prato do Dia",
      "porcao_referencia": "350g",
      "nutrientes": {
        "energia_kcal": 420,
        "energia_kj": 1757.3,
        "carboidratos_g": 12,
        "proteinas_g": 35,
        "gorduras_totais_g": 26,
        "gorduras_saturadas_g": 14,
        "gorduras_trans_g": 0.1,
        "fibra_alimentar_g": 2,
        "acucares_totais_g": 5,
        "sodio_mg": 780,
        "colesterol_mg": null,
        "alcool_g": 0,
        "calcio_mg": 75,
        "ferro_mg": 1.4,
        "potassio_mg": 580,
        "vitamina_c_mg": 6,
        "vitamina_A_mcg": 95,
        "vitamina_D_mcg": 0.3,
        "vitamina_E_mg": 0.8,
        "vitamina_B12_mcg": 0.4,
        "folato_mcg": 20,
        "fosforo_mg": 320,
        "magnesio_mg": 38,
        "zinco_mg": 1.8,
        "selenio_mcg": 28,
        "manganes_mg": 0.2,
        "cobre_mg": 0.1
      },
      "fonte": "Baseado em tabelas TACO (UNICAMP), IBGE e literatura nutricional brasileira",
      "observacoes": "Frango em molho cremoso com creme de leite e champignon",
      "tags": [
        "prato feito",
        "preparação brasileira",
        "Prato do Dia",
        "Peito de frango",
        "Creme de leite",
        "Extrato de tomate",
        "Champignon em conserva",
        "Cebola",
        "Alho",
        "Manteiga",
        "Mostarda",
        "Sal e temperos"
      ],
      "ingredientes": [
        {
          "nome": "Peito de frango",
          "quantidade_g": 150
        },
        {
          "nome": "Creme de leite",
          "quantidade_g": 80
        },
        {
          "nome": "Extrato de tomate",
          "quantidade_g": 30
        },
        {
          "nome": "Champignon em conserva",
          "quantidade_g": 40
        },
        {
          "nome": "Cebola",
          "quantidade_g": 30
        },
        {
          "nome": "Alho",
          "quantidade_g": 5
        },
        {
          "nome": "Manteiga",
          "quantidade_g": 10
        },
        {
          "nome": "Mostarda",
          "quantidade_g": 5
        },
        {
          "nome": "Sal e temperos",
          "quantidade_g": 5
        }
      ]
    },
    {
      "id": "lasanha_a_parmegiana_de_frango",
      "nome": "Lasanha à Parmegiana de Frango",
      "categoria": "Pratos feitos brasileiros",
      "subcategoria": "Massa / Italiano-Brasileiro",
      "porcao_referencia": "400g",
      "nutrientes": {
        "energia_kcal": 610,
        "energia_kj": 2552.2,
        "carboidratos_g": 32,
        "proteinas_g": 48,
        "gorduras_totais_g": 30,
        "gorduras_saturadas_g": 12,
        "gorduras_trans_g": 0.2,
        "fibra_alimentar_g": 2,
        "acucares_totais_g": 6,
        "sodio_mg": 1100,
        "colesterol_mg": null,
        "alcool_g": 0,
        "calcio_mg": 360,
        "ferro_mg": 2.2,
        "potassio_mg": 520,
        "vitamina_c_mg": 8,
        "vitamina_A_mcg": 120,
        "vitamina_D_mcg": 0.4,
        "vitamina_E_mg": 2.1,
        "vitamina_B12_mcg": 0.8,
        "folato_mcg": 35,
        "fosforo_mg": 480,
        "magnesio_mg": 42,
        "zinco_mg": 3.4,
        "selenio_mcg": 26,
        "manganes_mg": 0.3,
        "cobre_mg": 0.2
      },
      "fonte": "Baseado em tabelas TACO (UNICAMP), IBGE e literatura nutricional brasileira",
      "observacoes": "Filé de frango empanado com molho de tomate e queijo gratinado, servido com massa",
      "tags": [
        "prato feito",
        "preparação brasileira",
        "Massa / Italiano-Brasileiro",
        "Peito de frango empanado",
        "Farinha de trigo (empanamento)",
        "Ovo",
        "Farinha de rosca",
        "Molho de tomate",
        "Queijo mussarela",
        "Queijo parmesão ralado",
        "Óleo de soja",
        "Presunto"
      ],
      "ingredientes": [
        {
          "nome": "Peito de frango empanado",
          "quantidade_g": 150
        },
        {
          "nome": "Farinha de trigo (empanamento)",
          "quantidade_g": 20
        },
        {
          "nome": "Ovo",
          "quantidade_g": 30
        },
        {
          "nome": "Farinha de rosca",
          "quantidade_g": 20
        },
        {
          "nome": "Molho de tomate",
          "quantidade_g": 80
        },
        {
          "nome": "Queijo mussarela",
          "quantidade_g": 60
        },
        {
          "nome": "Queijo parmesão ralado",
          "quantidade_g": 20
        },
        {
          "nome": "Óleo de soja",
          "quantidade_g": 20
        },
        {
          "nome": "Presunto",
          "quantidade_g": 30
        }
      ]
    },
    {
      "id": "lasanha_de_carne_ao_forno",
      "nome": "Lasanha de Carne ao Forno",
      "categoria": "Pratos feitos brasileiros",
      "subcategoria": "Massa",
      "porcao_referencia": "400g",
      "nutrientes": {
        "energia_kcal": 580,
        "energia_kj": 2426.7,
        "carboidratos_g": 52,
        "proteinas_g": 38,
        "gorduras_totais_g": 22,
        "gorduras_saturadas_g": 10,
        "gorduras_trans_g": 0.4,
        "fibra_alimentar_g": 3,
        "acucares_totais_g": 7,
        "sodio_mg": 820,
        "colesterol_mg": null,
        "alcool_g": 0,
        "calcio_mg": 280,
        "ferro_mg": 3.8,
        "potassio_mg": 560,
        "vitamina_c_mg": 10,
        "vitamina_A_mcg": 110,
        "vitamina_D_mcg": 0.3,
        "vitamina_E_mg": 1.5,
        "vitamina_B12_mcg": 2.2,
        "folato_mcg": 42,
        "fosforo_mg": 400,
        "magnesio_mg": 48,
        "zinco_mg": 4.2,
        "selenio_mcg": 20,
        "manganes_mg": 0.8,
        "cobre_mg": 0.2
      },
      "fonte": "Baseado em tabelas TACO (UNICAMP), IBGE e literatura nutricional brasileira",
      "observacoes": "Massa intercalada com molho bolonhesa de carne moída e bechamel",
      "tags": [
        "prato feito",
        "preparação brasileira",
        "Massa",
        "Massa de lasanha",
        "Carne moída bovina",
        "Molho de tomate",
        "Leite integral",
        "Farinha de trigo",
        "Manteiga",
        "Queijo mussarela",
        "Cebola",
        "Alho",
        "Extrato de tomate"
      ],
      "ingredientes": [
        {
          "nome": "Massa de lasanha",
          "quantidade_g": 100
        },
        {
          "nome": "Carne moída bovina",
          "quantidade_g": 120
        },
        {
          "nome": "Molho de tomate",
          "quantidade_g": 80
        },
        {
          "nome": "Leite integral",
          "quantidade_g": 60
        },
        {
          "nome": "Farinha de trigo",
          "quantidade_g": 10
        },
        {
          "nome": "Manteiga",
          "quantidade_g": 10
        },
        {
          "nome": "Queijo mussarela",
          "quantidade_g": 60
        },
        {
          "nome": "Cebola",
          "quantidade_g": 20
        },
        {
          "nome": "Alho",
          "quantidade_g": 5
        },
        {
          "nome": "Extrato de tomate",
          "quantidade_g": 20
        }
      ]
    },
    {
      "id": "arroz_com_feijao_e_bife",
      "nome": "Arroz com Feijão e Bife",
      "categoria": "Pratos feitos brasileiros",
      "subcategoria": "Prato do Dia Clássico",
      "porcao_referencia": "450g",
      "nutrientes": {
        "energia_kcal": 550,
        "energia_kj": 2301.2,
        "carboidratos_g": 62,
        "proteinas_g": 40,
        "gorduras_totais_g": 12,
        "gorduras_saturadas_g": 3.5,
        "gorduras_trans_g": 0.1,
        "fibra_alimentar_g": 8,
        "acucares_totais_g": 2,
        "sodio_mg": 620,
        "colesterol_mg": null,
        "alcool_g": 0,
        "calcio_mg": 55,
        "ferro_mg": 5.5,
        "potassio_mg": 720,
        "vitamina_c_mg": 2,
        "vitamina_A_mcg": 8,
        "vitamina_D_mcg": 0.1,
        "vitamina_E_mg": 1.2,
        "vitamina_B12_mcg": 2.1,
        "folato_mcg": 120,
        "fosforo_mg": 380,
        "magnesio_mg": 68,
        "zinco_mg": 4.8,
        "selenio_mcg": 18,
        "manganes_mg": 1.2,
        "cobre_mg": 0.4
      },
      "fonte": "Baseado em tabelas TACO (UNICAMP), IBGE e literatura nutricional brasileira",
      "observacoes": "A base da culinária brasileira: arroz branco, feijão carioca e bife grelhado",
      "tags": [
        "prato feito",
        "preparação brasileira",
        "Prato do Dia Clássico",
        "Arroz branco cozido",
        "Feijão carioca cozido",
        "Bife de alcatra",
        "Alho",
        "Cebola",
        "Óleo de soja",
        "Sal"
      ],
      "ingredientes": [
        {
          "nome": "Arroz branco cozido",
          "quantidade_g": 150
        },
        {
          "nome": "Feijão carioca cozido",
          "quantidade_g": 120
        },
        {
          "nome": "Bife de alcatra",
          "quantidade_g": 120
        },
        {
          "nome": "Alho",
          "quantidade_g": 8
        },
        {
          "nome": "Cebola",
          "quantidade_g": 20
        },
        {
          "nome": "Óleo de soja",
          "quantidade_g": 10
        },
        {
          "nome": "Sal",
          "quantidade_g": 3
        }
      ]
    },
    {
      "id": "frango_assado_com_batata",
      "nome": "Frango Assado com Batata",
      "categoria": "Pratos feitos brasileiros",
      "subcategoria": "Prato Assado",
      "porcao_referencia": "400g",
      "nutrientes": {
        "energia_kcal": 480,
        "energia_kj": 2008.3,
        "carboidratos_g": 28,
        "proteinas_g": 38,
        "gorduras_totais_g": 22,
        "gorduras_saturadas_g": 6,
        "gorduras_trans_g": 0.1,
        "fibra_alimentar_g": 3,
        "acucares_totais_g": 2,
        "sodio_mg": 520,
        "colesterol_mg": null,
        "alcool_g": 0,
        "calcio_mg": 40,
        "ferro_mg": 2,
        "potassio_mg": 870,
        "vitamina_c_mg": 18,
        "vitamina_A_mcg": 40,
        "vitamina_D_mcg": 0.3,
        "vitamina_E_mg": 2.5,
        "vitamina_B12_mcg": 0.6,
        "folato_mcg": 28,
        "fosforo_mg": 350,
        "magnesio_mg": 52,
        "zinco_mg": 2.6,
        "selenio_mcg": 24,
        "manganes_mg": 0.4,
        "cobre_mg": 0.2
      },
      "fonte": "Baseado em tabelas TACO (UNICAMP), IBGE e literatura nutricional brasileira",
      "observacoes": "Frango inteiro ou em pedaços assado com batatas ao redor, temperado com ervas",
      "tags": [
        "prato feito",
        "preparação brasileira",
        "Prato Assado",
        "Coxa e sobrecoxa de frango (com pele)",
        "Batata inglesa",
        "Alho",
        "Limão",
        "Azeite",
        "Alecrim",
        "Sal e pimenta"
      ],
      "ingredientes": [
        {
          "nome": "Coxa e sobrecoxa de frango (com pele)",
          "quantidade_g": 200
        },
        {
          "nome": "Batata inglesa",
          "quantidade_g": 150
        },
        {
          "nome": "Alho",
          "quantidade_g": 10
        },
        {
          "nome": "Limão",
          "quantidade_g": 20
        },
        {
          "nome": "Azeite",
          "quantidade_g": 10
        },
        {
          "nome": "Alecrim",
          "quantidade_g": 2
        },
        {
          "nome": "Sal e pimenta",
          "quantidade_g": 3
        }
      ]
    },
    {
      "id": "moqueca_de_peixe_baiana",
      "nome": "Moqueca de Peixe (Baiana)",
      "categoria": "Pratos feitos brasileiros",
      "subcategoria": "Prato Regional - Nordeste",
      "porcao_referencia": "380g",
      "nutrientes": {
        "energia_kcal": 390,
        "energia_kj": 1631.8,
        "carboidratos_g": 10,
        "proteinas_g": 34,
        "gorduras_totais_g": 24,
        "gorduras_saturadas_g": 14,
        "gorduras_trans_g": 0,
        "fibra_alimentar_g": 3,
        "acucares_totais_g": 5,
        "sodio_mg": 480,
        "colesterol_mg": null,
        "alcool_g": 0,
        "calcio_mg": 60,
        "ferro_mg": 2.5,
        "potassio_mg": 780,
        "vitamina_c_mg": 62,
        "vitamina_A_mcg": 380,
        "vitamina_D_mcg": 8,
        "vitamina_E_mg": 3.2,
        "vitamina_B12_mcg": 2.8,
        "folato_mcg": 42,
        "fosforo_mg": 420,
        "magnesio_mg": 70,
        "zinco_mg": 1.8,
        "selenio_mcg": 48,
        "manganes_mg": 1.2,
        "cobre_mg": 0.3
      },
      "fonte": "Baseado em tabelas TACO (UNICAMP), IBGE e literatura nutricional brasileira",
      "observacoes": "Peixe cozido em leite de coco, azeite de dendê, tomate, pimentão e coentro",
      "tags": [
        "prato feito",
        "preparação brasileira",
        "Prato Regional - Nordeste",
        "Peixe (badejo ou robalo)",
        "Leite de coco",
        "Azeite de dendê",
        "Tomate",
        "Pimentão verde",
        "Pimentão vermelho",
        "Cebola",
        "Coentro",
        "Limão",
        "Alho"
      ],
      "ingredientes": [
        {
          "nome": "Peixe (badejo ou robalo)",
          "quantidade_g": 200
        },
        {
          "nome": "Leite de coco",
          "quantidade_g": 80
        },
        {
          "nome": "Azeite de dendê",
          "quantidade_g": 15
        },
        {
          "nome": "Tomate",
          "quantidade_g": 40
        },
        {
          "nome": "Pimentão verde",
          "quantidade_g": 30
        },
        {
          "nome": "Pimentão vermelho",
          "quantidade_g": 30
        },
        {
          "nome": "Cebola",
          "quantidade_g": 30
        },
        {
          "nome": "Coentro",
          "quantidade_g": 5
        },
        {
          "nome": "Limão",
          "quantidade_g": 10
        },
        {
          "nome": "Alho",
          "quantidade_g": 8
        }
      ]
    },
    {
      "id": "picanha_na_brasa",
      "nome": "Picanha na Brasa",
      "categoria": "Pratos feitos brasileiros",
      "subcategoria": "Churrasco",
      "porcao_referencia": "300g",
      "nutrientes": {
        "energia_kcal": 560,
        "energia_kj": 2343,
        "carboidratos_g": 0,
        "proteinas_g": 48,
        "gorduras_totais_g": 40,
        "gorduras_saturadas_g": 16,
        "gorduras_trans_g": 1.2,
        "fibra_alimentar_g": 0,
        "acucares_totais_g": 0,
        "sodio_mg": 750,
        "colesterol_mg": null,
        "alcool_g": 0,
        "calcio_mg": 22,
        "ferro_mg": 3.8,
        "potassio_mg": 580,
        "vitamina_c_mg": 0,
        "vitamina_A_mcg": 0,
        "vitamina_D_mcg": 0.2,
        "vitamina_E_mg": 0.5,
        "vitamina_B12_mcg": 4.5,
        "folato_mcg": 12,
        "fosforo_mg": 480,
        "magnesio_mg": 38,
        "zinco_mg": 8.5,
        "selenio_mcg": 36,
        "manganes_mg": 0.05,
        "cobre_mg": 0.1
      },
      "fonte": "Baseado em tabelas TACO (UNICAMP), IBGE e literatura nutricional brasileira",
      "observacoes": "Corte nobre bovino grelhado na brasa ou churrasqueira, com sal grosso",
      "tags": [
        "prato feito",
        "preparação brasileira",
        "Churrasco",
        "Picanha bovina (com capa de gordura)",
        "Sal grosso",
        "Alho (opcional)"
      ],
      "ingredientes": [
        {
          "nome": "Picanha bovina (com capa de gordura)",
          "quantidade_g": 280
        },
        {
          "nome": "Sal grosso",
          "quantidade_g": 5
        },
        {
          "nome": "Alho (opcional)",
          "quantidade_g": 5
        }
      ]
    },
    {
      "id": "pamonha_de_milho",
      "nome": "Pamonha de Milho",
      "categoria": "Pratos feitos brasileiros",
      "subcategoria": "Comida Caipira / Festa Junina",
      "porcao_referencia": "250g",
      "nutrientes": {
        "energia_kcal": 320,
        "energia_kj": 1338.9,
        "carboidratos_g": 58,
        "proteinas_g": 7,
        "gorduras_totais_g": 8,
        "gorduras_saturadas_g": 6,
        "gorduras_trans_g": 0.1,
        "fibra_alimentar_g": 4,
        "acucares_totais_g": 18,
        "sodio_mg": 280,
        "colesterol_mg": null,
        "alcool_g": 0,
        "calcio_mg": 18,
        "ferro_mg": 1.2,
        "potassio_mg": 340,
        "vitamina_c_mg": 8,
        "vitamina_A_mcg": 28,
        "vitamina_D_mcg": 0.1,
        "vitamina_E_mg": 0.5,
        "vitamina_B12_mcg": 0.1,
        "folato_mcg": 32,
        "fosforo_mg": 120,
        "magnesio_mg": 38,
        "zinco_mg": 0.8,
        "selenio_mcg": 6,
        "manganes_mg": 0.4,
        "cobre_mg": 0.1
      },
      "fonte": "Baseado em tabelas TACO (UNICAMP), IBGE e literatura nutricional brasileira",
      "observacoes": "Massa de milho verde ralado com leite de coco cozida em palha de milho",
      "tags": [
        "prato feito",
        "preparação brasileira",
        "Comida Caipira / Festa Junina",
        "Milho verde ralado",
        "Leite de coco",
        "Açúcar",
        "Sal",
        "Manteiga"
      ],
      "ingredientes": [
        {
          "nome": "Milho verde ralado",
          "quantidade_g": 180
        },
        {
          "nome": "Leite de coco",
          "quantidade_g": 50
        },
        {
          "nome": "Açúcar",
          "quantidade_g": 15
        },
        {
          "nome": "Sal",
          "quantidade_g": 2
        },
        {
          "nome": "Manteiga",
          "quantidade_g": 8
        }
      ]
    },
    {
      "id": "tutu_de_feijao_com_costelinha",
      "nome": "Tutu de Feijão com Costelinha",
      "categoria": "Pratos feitos brasileiros",
      "subcategoria": "Prato Regional - Minas Gerais",
      "porcao_referencia": "400g",
      "nutrientes": {
        "energia_kcal": 580,
        "energia_kj": 2426.7,
        "carboidratos_g": 46,
        "proteinas_g": 38,
        "gorduras_totais_g": 24,
        "gorduras_saturadas_g": 8,
        "gorduras_trans_g": 0.2,
        "fibra_alimentar_g": 10,
        "acucares_totais_g": 2,
        "sodio_mg": 920,
        "colesterol_mg": null,
        "alcool_g": 0,
        "calcio_mg": 65,
        "ferro_mg": 4.8,
        "potassio_mg": 680,
        "vitamina_c_mg": 3,
        "vitamina_A_mcg": 10,
        "vitamina_D_mcg": 0.3,
        "vitamina_E_mg": 1,
        "vitamina_B12_mcg": 1.5,
        "folato_mcg": 140,
        "fosforo_mg": 360,
        "magnesio_mg": 62,
        "zinco_mg": 4.2,
        "selenio_mcg": 18,
        "manganes_mg": 0.8,
        "cobre_mg": 0.35
      },
      "fonte": "Baseado em tabelas TACO (UNICAMP), IBGE e literatura nutricional brasileira",
      "observacoes": "Feijão cremoso engrossado com farinha de mandioca e costelinha de porco",
      "tags": [
        "prato feito",
        "preparação brasileira",
        "Prato Regional - Minas Gerais",
        "Feijão carioca cozido",
        "Farinha de mandioca",
        "Costelinha de porco",
        "Bacon",
        "Cebola",
        "Alho",
        "Óleo"
      ],
      "ingredientes": [
        {
          "nome": "Feijão carioca cozido",
          "quantidade_g": 150
        },
        {
          "nome": "Farinha de mandioca",
          "quantidade_g": 40
        },
        {
          "nome": "Costelinha de porco",
          "quantidade_g": 120
        },
        {
          "nome": "Bacon",
          "quantidade_g": 30
        },
        {
          "nome": "Cebola",
          "quantidade_g": 20
        },
        {
          "nome": "Alho",
          "quantidade_g": 8
        },
        {
          "nome": "Óleo",
          "quantidade_g": 8
        }
      ]
    },
    {
      "id": "coxinha_de_frango",
      "nome": "Coxinha de Frango",
      "categoria": "Pratos feitos brasileiros",
      "subcategoria": "Salgado / Lanche",
      "porcao_referencia": "120g",
      "nutrientes": {
        "energia_kcal": 280,
        "energia_kj": 1171.5,
        "carboidratos_g": 28,
        "proteinas_g": 14,
        "gorduras_totais_g": 12,
        "gorduras_saturadas_g": 3.5,
        "gorduras_trans_g": 0.1,
        "fibra_alimentar_g": 1.5,
        "acucares_totais_g": 1.5,
        "sodio_mg": 420,
        "colesterol_mg": null,
        "alcool_g": 0,
        "calcio_mg": 45,
        "ferro_mg": 1.2,
        "potassio_mg": 240,
        "vitamina_c_mg": 3,
        "vitamina_A_mcg": 30,
        "vitamina_D_mcg": 0.2,
        "vitamina_E_mg": 1.5,
        "vitamina_B12_mcg": 0.2,
        "folato_mcg": 18,
        "fosforo_mg": 140,
        "magnesio_mg": 18,
        "zinco_mg": 1,
        "selenio_mcg": 10,
        "manganes_mg": 0.2,
        "cobre_mg": 0.1
      },
      "fonte": "Baseado em tabelas TACO (UNICAMP), IBGE e literatura nutricional brasileira",
      "observacoes": "Massa de batata ou farinha recheada com frango desfiado e requeijão, frita",
      "tags": [
        "prato feito",
        "preparação brasileira",
        "Salgado / Lanche",
        "Farinha de trigo",
        "Batata cozida",
        "Frango desfiado",
        "Requeijão cremoso",
        "Cebola",
        "Farinha de rosca",
        "Ovo",
        "Óleo para fritar"
      ],
      "ingredientes": [
        {
          "nome": "Farinha de trigo",
          "quantidade_g": 30
        },
        {
          "nome": "Batata cozida",
          "quantidade_g": 30
        },
        {
          "nome": "Frango desfiado",
          "quantidade_g": 30
        },
        {
          "nome": "Requeijão cremoso",
          "quantidade_g": 15
        },
        {
          "nome": "Cebola",
          "quantidade_g": 8
        },
        {
          "nome": "Farinha de rosca",
          "quantidade_g": 8
        },
        {
          "nome": "Ovo",
          "quantidade_g": 10
        },
        {
          "nome": "Óleo para fritar",
          "quantidade_g": 12
        }
      ]
    },
    {
      "id": "pao_de_queijo",
      "nome": "Pão de Queijo",
      "categoria": "Pratos feitos brasileiros",
      "subcategoria": "Café da Manhã / Lanche",
      "porcao_referencia": "80g",
      "nutrientes": {
        "energia_kcal": 240,
        "energia_kj": 1004.2,
        "carboidratos_g": 32,
        "proteinas_g": 7,
        "gorduras_totais_g": 9,
        "gorduras_saturadas_g": 3.5,
        "gorduras_trans_g": 0.1,
        "fibra_alimentar_g": 0.5,
        "acucares_totais_g": 1,
        "sodio_mg": 280,
        "colesterol_mg": null,
        "alcool_g": 0,
        "calcio_mg": 160,
        "ferro_mg": 0.5,
        "potassio_mg": 80,
        "vitamina_c_mg": 0,
        "vitamina_A_mcg": 55,
        "vitamina_D_mcg": 0.5,
        "vitamina_E_mg": 0.8,
        "vitamina_B12_mcg": 0.3,
        "folato_mcg": 8,
        "fosforo_mg": 140,
        "magnesio_mg": 12,
        "zinco_mg": 0.9,
        "selenio_mcg": 8,
        "manganes_mg": 0.1,
        "cobre_mg": 0.05
      },
      "fonte": "Baseado em tabelas TACO (UNICAMP), IBGE e literatura nutricional brasileira",
      "observacoes": "Bolinha de polvilho azedo com queijo mineiro, tradicional de Minas Gerais",
      "tags": [
        "prato feito",
        "preparação brasileira",
        "Café da Manhã / Lanche",
        "Polvilho azedo",
        "Queijo minas curado ralado",
        "Leite integral",
        "Ovo",
        "Óleo",
        "Sal"
      ],
      "ingredientes": [
        {
          "nome": "Polvilho azedo",
          "quantidade_g": 40
        },
        {
          "nome": "Queijo minas curado ralado",
          "quantidade_g": 20
        },
        {
          "nome": "Leite integral",
          "quantidade_g": 20
        },
        {
          "nome": "Ovo",
          "quantidade_g": 15
        },
        {
          "nome": "Óleo",
          "quantidade_g": 8
        },
        {
          "nome": "Sal",
          "quantidade_g": 2
        }
      ]
    },
    {
      "id": "virado_a_paulista",
      "nome": "Virado à Paulista",
      "categoria": "Pratos feitos brasileiros",
      "subcategoria": "Prato Regional - São Paulo",
      "porcao_referencia": "500g",
      "nutrientes": {
        "energia_kcal": 680,
        "energia_kj": 2845.1,
        "carboidratos_g": 62,
        "proteinas_g": 38,
        "gorduras_totais_g": 28,
        "gorduras_saturadas_g": 8,
        "gorduras_trans_g": 0.2,
        "fibra_alimentar_g": 10,
        "acucares_totais_g": 12,
        "sodio_mg": 980,
        "colesterol_mg": null,
        "alcool_g": 0,
        "calcio_mg": 140,
        "ferro_mg": 5.8,
        "potassio_mg": 920,
        "vitamina_c_mg": 28,
        "vitamina_A_mcg": 220,
        "vitamina_D_mcg": 0.6,
        "vitamina_E_mg": 2.8,
        "vitamina_B12_mcg": 1.2,
        "folato_mcg": 145,
        "fosforo_mg": 420,
        "magnesio_mg": 72,
        "zinco_mg": 4,
        "selenio_mcg": 20,
        "manganes_mg": 1.5,
        "cobre_mg": 0.4
      },
      "fonte": "Baseado em tabelas TACO (UNICAMP), IBGE e literatura nutricional brasileira",
      "observacoes": "Feijão virado com farinha, linguiça, ovo frito, costelinha, couve refogada e banana frita",
      "tags": [
        "prato feito",
        "preparação brasileira",
        "Prato Regional - São Paulo",
        "Feijão carioca virado",
        "Farinha de mandioca torrada",
        "Linguiça calabresa",
        "Ovo frito",
        "Costelinha de porco",
        "Couve manteiga refogada",
        "Banana prata frita",
        "Óleo"
      ],
      "ingredientes": [
        {
          "nome": "Feijão carioca virado",
          "quantidade_g": 130
        },
        {
          "nome": "Farinha de mandioca torrada",
          "quantidade_g": 30
        },
        {
          "nome": "Linguiça calabresa",
          "quantidade_g": 60
        },
        {
          "nome": "Ovo frito",
          "quantidade_g": 55
        },
        {
          "nome": "Costelinha de porco",
          "quantidade_g": 80
        },
        {
          "nome": "Couve manteiga refogada",
          "quantidade_g": 60
        },
        {
          "nome": "Banana prata frita",
          "quantidade_g": 80
        },
        {
          "nome": "Óleo",
          "quantidade_g": 15
        }
      ]
    },
    {
      "id": "vatapa",
      "nome": "Vatapá",
      "categoria": "Pratos feitos brasileiros",
      "subcategoria": "Prato Regional - Bahia",
      "porcao_referencia": "300g",
      "nutrientes": {
        "energia_kcal": 490,
        "energia_kj": 2050.2,
        "carboidratos_g": 32,
        "proteinas_g": 22,
        "gorduras_totais_g": 32,
        "gorduras_saturadas_g": 16,
        "gorduras_trans_g": 0,
        "fibra_alimentar_g": 4,
        "acucares_totais_g": 5,
        "sodio_mg": 860,
        "colesterol_mg": null,
        "alcool_g": 0,
        "calcio_mg": 120,
        "ferro_mg": 4.2,
        "potassio_mg": 480,
        "vitamina_c_mg": 4,
        "vitamina_A_mcg": 290,
        "vitamina_D_mcg": 1.2,
        "vitamina_E_mg": 4.5,
        "vitamina_B12_mcg": 1.5,
        "folato_mcg": 38,
        "fosforo_mg": 280,
        "magnesio_mg": 62,
        "zinco_mg": 2.8,
        "selenio_mcg": 38,
        "manganes_mg": 0.9,
        "cobre_mg": 0.5
      },
      "fonte": "Baseado em tabelas TACO (UNICAMP), IBGE e literatura nutricional brasileira",
      "observacoes": "Creme espesso de pão, leite de coco, dendê, amendoim e camarão seco",
      "tags": [
        "prato feito",
        "preparação brasileira",
        "Prato Regional - Bahia",
        "Pão de forma",
        "Leite de coco",
        "Azeite de dendê",
        "Amendoim torrado",
        "Castanha de caju",
        "Camarão seco",
        "Cebola",
        "Gengibre",
        "Coentro"
      ],
      "ingredientes": [
        {
          "nome": "Pão de forma",
          "quantidade_g": 60
        },
        {
          "nome": "Leite de coco",
          "quantidade_g": 80
        },
        {
          "nome": "Azeite de dendê",
          "quantidade_g": 20
        },
        {
          "nome": "Amendoim torrado",
          "quantidade_g": 30
        },
        {
          "nome": "Castanha de caju",
          "quantidade_g": 20
        },
        {
          "nome": "Camarão seco",
          "quantidade_g": 40
        },
        {
          "nome": "Cebola",
          "quantidade_g": 20
        },
        {
          "nome": "Gengibre",
          "quantidade_g": 5
        },
        {
          "nome": "Coentro",
          "quantidade_g": 3
        }
      ]
    },
    {
      "id": "caldo_de_feijao",
      "nome": "Caldo de Feijão",
      "categoria": "Pratos feitos brasileiros",
      "subcategoria": "Sopa / Caldo",
      "porcao_referencia": "350g",
      "nutrientes": {
        "energia_kcal": 320,
        "energia_kj": 1338.9,
        "carboidratos_g": 38,
        "proteinas_g": 20,
        "gorduras_totais_g": 10,
        "gorduras_saturadas_g": 3.5,
        "gorduras_trans_g": 0.1,
        "fibra_alimentar_g": 11,
        "acucares_totais_g": 2,
        "sodio_mg": 760,
        "colesterol_mg": null,
        "alcool_g": 0,
        "calcio_mg": 60,
        "ferro_mg": 4.2,
        "potassio_mg": 620,
        "vitamina_c_mg": 5,
        "vitamina_A_mcg": 15,
        "vitamina_D_mcg": 0.1,
        "vitamina_E_mg": 0.8,
        "vitamina_B12_mcg": 0.6,
        "folato_mcg": 130,
        "fosforo_mg": 260,
        "magnesio_mg": 58,
        "zinco_mg": 2.5,
        "selenio_mcg": 12,
        "manganes_mg": 0.7,
        "cobre_mg": 0.3
      },
      "fonte": "Baseado em tabelas TACO (UNICAMP), IBGE e literatura nutricional brasileira",
      "observacoes": "Caldo grosso de feijão com bacon, linguiça e temperos, servido quente",
      "tags": [
        "prato feito",
        "preparação brasileira",
        "Sopa / Caldo",
        "Feijão carioca cozido amassado",
        "Bacon",
        "Linguiça",
        "Cebola",
        "Alho",
        "Coentro/cheiro-verde",
        "Óleo"
      ],
      "ingredientes": [
        {
          "nome": "Feijão carioca cozido amassado",
          "quantidade_g": 180
        },
        {
          "nome": "Bacon",
          "quantidade_g": 30
        },
        {
          "nome": "Linguiça",
          "quantidade_g": 40
        },
        {
          "nome": "Cebola",
          "quantidade_g": 20
        },
        {
          "nome": "Alho",
          "quantidade_g": 8
        },
        {
          "nome": "Coentro/cheiro-verde",
          "quantidade_g": 5
        },
        {
          "nome": "Óleo",
          "quantidade_g": 5
        }
      ]
    },
    {
      "id": "peixe_frito_com_pirao",
      "nome": "Peixe Frito com Pirão",
      "categoria": "Pratos feitos brasileiros",
      "subcategoria": "Prato de Peixe",
      "porcao_referencia": "400g",
      "nutrientes": {
        "energia_kcal": 420,
        "energia_kj": 1757.3,
        "carboidratos_g": 38,
        "proteinas_g": 32,
        "gorduras_totais_g": 14,
        "gorduras_saturadas_g": 2.5,
        "gorduras_trans_g": 0,
        "fibra_alimentar_g": 2,
        "acucares_totais_g": 1,
        "sodio_mg": 580,
        "colesterol_mg": null,
        "alcool_g": 0,
        "calcio_mg": 40,
        "ferro_mg": 1.8,
        "potassio_mg": 520,
        "vitamina_c_mg": 10,
        "vitamina_A_mcg": 20,
        "vitamina_D_mcg": 6,
        "vitamina_E_mg": 3.8,
        "vitamina_B12_mcg": 2.2,
        "folato_mcg": 22,
        "fosforo_mg": 380,
        "magnesio_mg": 45,
        "zinco_mg": 1.2,
        "selenio_mcg": 42,
        "manganes_mg": 0.5,
        "cobre_mg": 0.15
      },
      "fonte": "Baseado em tabelas TACO (UNICAMP), IBGE e literatura nutricional brasileira",
      "observacoes": "Peixe empanado e frito com pirão (caldo de peixe engrossado com farinha de mandioca)",
      "tags": [
        "prato feito",
        "preparação brasileira",
        "Prato de Peixe",
        "Peixe (tilápia ou merluza)",
        "Farinha de trigo (empanamento)",
        "Óleo para fritar",
        "Farinha de mandioca",
        "Caldo de peixe",
        "Limão",
        "Sal e temperos"
      ],
      "ingredientes": [
        {
          "nome": "Peixe (tilápia ou merluza)",
          "quantidade_g": 180
        },
        {
          "nome": "Farinha de trigo (empanamento)",
          "quantidade_g": 20
        },
        {
          "nome": "Óleo para fritar",
          "quantidade_g": 20
        },
        {
          "nome": "Farinha de mandioca",
          "quantidade_g": 40
        },
        {
          "nome": "Caldo de peixe",
          "quantidade_g": 100
        },
        {
          "nome": "Limão",
          "quantidade_g": 15
        },
        {
          "nome": "Sal e temperos",
          "quantidade_g": 5
        }
      ]
    },
    {
      "id": "escondidinho_de_carne_seca",
      "nome": "Escondidinho de Carne Seca",
      "categoria": "Pratos feitos brasileiros",
      "subcategoria": "Prato Assado",
      "porcao_referencia": "380g",
      "nutrientes": {
        "energia_kcal": 540,
        "energia_kj": 2259.4,
        "carboidratos_g": 44,
        "proteinas_g": 38,
        "gorduras_totais_g": 20,
        "gorduras_saturadas_g": 9,
        "gorduras_trans_g": 0.2,
        "fibra_alimentar_g": 3,
        "acucares_totais_g": 4,
        "sodio_mg": 1280,
        "colesterol_mg": null,
        "alcool_g": 0,
        "calcio_mg": 180,
        "ferro_mg": 3.5,
        "potassio_mg": 680,
        "vitamina_c_mg": 20,
        "vitamina_A_mcg": 90,
        "vitamina_D_mcg": 0.3,
        "vitamina_E_mg": 1.2,
        "vitamina_B12_mcg": 2.8,
        "folato_mcg": 35,
        "fosforo_mg": 360,
        "magnesio_mg": 44,
        "zinco_mg": 5,
        "selenio_mcg": 24,
        "manganes_mg": 0.5,
        "cobre_mg": 0.2
      },
      "fonte": "Baseado em tabelas TACO (UNICAMP), IBGE e literatura nutricional brasileira",
      "observacoes": "Carne seca desfiada coberta por purê de mandioca e queijo gratinado",
      "tags": [
        "prato feito",
        "preparação brasileira",
        "Prato Assado",
        "Carne seca dessalgada e desfiada",
        "Mandioca cozida",
        "Leite integral",
        "Manteiga",
        "Queijo mussarela",
        "Cebola",
        "Alho"
      ],
      "ingredientes": [
        {
          "nome": "Carne seca dessalgada e desfiada",
          "quantidade_g": 150
        },
        {
          "nome": "Mandioca cozida",
          "quantidade_g": 180
        },
        {
          "nome": "Leite integral",
          "quantidade_g": 30
        },
        {
          "nome": "Manteiga",
          "quantidade_g": 15
        },
        {
          "nome": "Queijo mussarela",
          "quantidade_g": 40
        },
        {
          "nome": "Cebola",
          "quantidade_g": 20
        },
        {
          "nome": "Alho",
          "quantidade_g": 5
        }
      ]
    },
    {
      "id": "acaraje",
      "nome": "Acarajé",
      "categoria": "Pratos feitos brasileiros",
      "subcategoria": "Prato Regional - Bahia / Street Food",
      "porcao_referencia": "250g",
      "nutrientes": {
        "energia_kcal": 410,
        "energia_kj": 1715.4,
        "carboidratos_g": 38,
        "proteinas_g": 20,
        "gorduras_totais_g": 20,
        "gorduras_saturadas_g": 9,
        "gorduras_trans_g": 0,
        "fibra_alimentar_g": 8,
        "acucares_totais_g": 3,
        "sodio_mg": 720,
        "colesterol_mg": null,
        "alcool_g": 0,
        "calcio_mg": 90,
        "ferro_mg": 5.5,
        "potassio_mg": 480,
        "vitamina_c_mg": 12,
        "vitamina_A_mcg": 310,
        "vitamina_D_mcg": 1,
        "vitamina_E_mg": 3.5,
        "vitamina_B12_mcg": 1.2,
        "folato_mcg": 160,
        "fosforo_mg": 220,
        "magnesio_mg": 55,
        "zinco_mg": 2.5,
        "selenio_mcg": 20,
        "manganes_mg": 1.2,
        "cobre_mg": 0.45
      },
      "fonte": "Baseado em tabelas TACO (UNICAMP), IBGE e literatura nutricional brasileira",
      "observacoes": "Bolinho de feijão-fradinho frito no azeite de dendê recheado com vatapá, caruru e camarão",
      "tags": [
        "prato feito",
        "preparação brasileira",
        "Prato Regional - Bahia / Street Food",
        "Feijão-fradinho",
        "Azeite de dendê",
        "Cebola",
        "Vatapá",
        "Caruru",
        "Camarão seco",
        "Pimenta malagueta"
      ],
      "ingredientes": [
        {
          "nome": "Feijão-fradinho",
          "quantidade_g": 80
        },
        {
          "nome": "Azeite de dendê",
          "quantidade_g": 25
        },
        {
          "nome": "Cebola",
          "quantidade_g": 20
        },
        {
          "nome": "Vatapá",
          "quantidade_g": 50
        },
        {
          "nome": "Caruru",
          "quantidade_g": 40
        },
        {
          "nome": "Camarão seco",
          "quantidade_g": 25
        },
        {
          "nome": "Pimenta malagueta",
          "quantidade_g": 3
        }
      ]
    },
    {
      "id": "galinhada_mineira",
      "nome": "Galinhada Mineira",
      "categoria": "Pratos feitos brasileiros",
      "subcategoria": "Prato Regional - Minas Gerais",
      "porcao_referencia": "450g",
      "nutrientes": {
        "energia_kcal": 490,
        "energia_kj": 2050.2,
        "carboidratos_g": 58,
        "proteinas_g": 32,
        "gorduras_totais_g": 12,
        "gorduras_saturadas_g": 3,
        "gorduras_trans_g": 0.1,
        "fibra_alimentar_g": 5,
        "acucares_totais_g": 5,
        "sodio_mg": 480,
        "colesterol_mg": null,
        "alcool_g": 0,
        "calcio_mg": 45,
        "ferro_mg": 3.2,
        "potassio_mg": 680,
        "vitamina_c_mg": 38,
        "vitamina_A_mcg": 185,
        "vitamina_D_mcg": 0.2,
        "vitamina_E_mg": 1.8,
        "vitamina_B12_mcg": 0.5,
        "folato_mcg": 55,
        "fosforo_mg": 300,
        "magnesio_mg": 50,
        "zinco_mg": 2.4,
        "selenio_mcg": 22,
        "manganes_mg": 0.8,
        "cobre_mg": 0.2
      },
      "fonte": "Baseado em tabelas TACO (UNICAMP), IBGE e literatura nutricional brasileira",
      "observacoes": "Frango cozido com arroz, açafrão, milho, ervilha e pimentão",
      "tags": [
        "prato feito",
        "preparação brasileira",
        "Prato Regional - Minas Gerais",
        "Frango (coxa e sobrecoxa)",
        "Arroz branco",
        "Açafrão-da-terra (cúrcuma)",
        "Milho verde",
        "Ervilha",
        "Pimentão vermelho",
        "Tomate",
        "Cebola",
        "Alho",
        "Óleo"
      ],
      "ingredientes": [
        {
          "nome": "Frango (coxa e sobrecoxa)",
          "quantidade_g": 180
        },
        {
          "nome": "Arroz branco",
          "quantidade_g": 120
        },
        {
          "nome": "Açafrão-da-terra (cúrcuma)",
          "quantidade_g": 3
        },
        {
          "nome": "Milho verde",
          "quantidade_g": 40
        },
        {
          "nome": "Ervilha",
          "quantidade_g": 30
        },
        {
          "nome": "Pimentão vermelho",
          "quantidade_g": 30
        },
        {
          "nome": "Tomate",
          "quantidade_g": 30
        },
        {
          "nome": "Cebola",
          "quantidade_g": 20
        },
        {
          "nome": "Alho",
          "quantidade_g": 8
        },
        {
          "nome": "Óleo",
          "quantidade_g": 8
        }
      ]
    },
    {
      "id": "bolo_de_rolo",
      "nome": "Bolo de Rolo",
      "categoria": "Pratos feitos brasileiros",
      "subcategoria": "Doce / Sobremesa Regional - Pernambuco",
      "porcao_referencia": "100g",
      "nutrientes": {
        "energia_kcal": 310,
        "energia_kj": 1297,
        "carboidratos_g": 48,
        "proteinas_g": 4,
        "gorduras_totais_g": 12,
        "gorduras_saturadas_g": 7,
        "gorduras_trans_g": 0.3,
        "fibra_alimentar_g": 1,
        "acucares_totais_g": 36,
        "sodio_mg": 120,
        "colesterol_mg": null,
        "alcool_g": 0,
        "calcio_mg": 22,
        "ferro_mg": 0.8,
        "potassio_mg": 120,
        "vitamina_c_mg": 4,
        "vitamina_A_mcg": 120,
        "vitamina_D_mcg": 0.5,
        "vitamina_E_mg": 0.6,
        "vitamina_B12_mcg": 0.2,
        "folato_mcg": 12,
        "fosforo_mg": 70,
        "magnesio_mg": 8,
        "zinco_mg": 0.4,
        "selenio_mcg": 5,
        "manganes_mg": 0.2,
        "cobre_mg": 0.06
      },
      "fonte": "Baseado em tabelas TACO (UNICAMP), IBGE e literatura nutricional brasileira",
      "observacoes": "Massa fininha enrolada com recheio de goiabada, doce típico pernambucano",
      "tags": [
        "prato feito",
        "preparação brasileira",
        "Doce / Sobremesa Regional - Pernambuco",
        "Farinha de trigo",
        "Manteiga",
        "Ovos",
        "Açúcar",
        "Goiabada"
      ],
      "ingredientes": [
        {
          "nome": "Farinha de trigo",
          "quantidade_g": 35
        },
        {
          "nome": "Manteiga",
          "quantidade_g": 20
        },
        {
          "nome": "Ovos",
          "quantidade_g": 25
        },
        {
          "nome": "Açúcar",
          "quantidade_g": 15
        },
        {
          "nome": "Goiabada",
          "quantidade_g": 30
        }
      ]
    },
    {
      "id": "baiao_de_dois",
      "nome": "Baião de Dois",
      "categoria": "Pratos feitos brasileiros",
      "subcategoria": "Prato Regional - Nordeste",
      "porcao_referencia": "400g",
      "nutrientes": {
        "energia_kcal": 520,
        "energia_kj": 2175.7,
        "carboidratos_g": 56,
        "proteinas_g": 36,
        "gorduras_totais_g": 16,
        "gorduras_saturadas_g": 6,
        "gorduras_trans_g": 0.2,
        "fibra_alimentar_g": 8,
        "acucares_totais_g": 2,
        "sodio_mg": 1050,
        "colesterol_mg": null,
        "alcool_g": 0,
        "calcio_mg": 135,
        "ferro_mg": 5.2,
        "potassio_mg": 680,
        "vitamina_c_mg": 5,
        "vitamina_A_mcg": 180,
        "vitamina_D_mcg": 0.2,
        "vitamina_E_mg": 2.8,
        "vitamina_B12_mcg": 2,
        "folato_mcg": 155,
        "fosforo_mg": 340,
        "magnesio_mg": 65,
        "zinco_mg": 4.8,
        "selenio_mcg": 22,
        "manganes_mg": 1.1,
        "cobre_mg": 0.4
      },
      "fonte": "Baseado em tabelas TACO (UNICAMP), IBGE e literatura nutricional brasileira",
      "observacoes": "Arroz com feijão-de-corda ou feijão verde cozidos juntos, com queijo coalho e carne seca",
      "tags": [
        "prato feito",
        "preparação brasileira",
        "Prato Regional - Nordeste",
        "Arroz",
        "Feijão-de-corda",
        "Carne seca",
        "Queijo coalho",
        "Bacon",
        "Cebola",
        "Alho",
        "Azeite de dendê",
        "Coentro"
      ],
      "ingredientes": [
        {
          "nome": "Arroz",
          "quantidade_g": 100
        },
        {
          "nome": "Feijão-de-corda",
          "quantidade_g": 100
        },
        {
          "nome": "Carne seca",
          "quantidade_g": 80
        },
        {
          "nome": "Queijo coalho",
          "quantidade_g": 40
        },
        {
          "nome": "Bacon",
          "quantidade_g": 20
        },
        {
          "nome": "Cebola",
          "quantidade_g": 20
        },
        {
          "nome": "Alho",
          "quantidade_g": 8
        },
        {
          "nome": "Azeite de dendê",
          "quantidade_g": 8
        },
        {
          "nome": "Coentro",
          "quantidade_g": 3
        }
      ]
    },
    {
      "id": "tapioca_com_queijo_e_presunto",
      "nome": "Tapioca com Queijo e Presunto",
      "categoria": "Pratos feitos brasileiros",
      "subcategoria": "Café da Manhã / Lanche",
      "porcao_referencia": "150g",
      "nutrientes": {
        "energia_kcal": 320,
        "energia_kj": 1338.9,
        "carboidratos_g": 38,
        "proteinas_g": 18,
        "gorduras_totais_g": 10,
        "gorduras_saturadas_g": 5,
        "gorduras_trans_g": 0.1,
        "fibra_alimentar_g": 0,
        "acucares_totais_g": 1,
        "sodio_mg": 680,
        "colesterol_mg": null,
        "alcool_g": 0,
        "calcio_mg": 220,
        "ferro_mg": 0.8,
        "potassio_mg": 160,
        "vitamina_c_mg": 0,
        "vitamina_A_mcg": 60,
        "vitamina_D_mcg": 0.3,
        "vitamina_E_mg": 0.4,
        "vitamina_B12_mcg": 0.6,
        "folato_mcg": 10,
        "fosforo_mg": 240,
        "magnesio_mg": 12,
        "zinco_mg": 1.8,
        "selenio_mcg": 12,
        "manganes_mg": 0.1,
        "cobre_mg": 0.08
      },
      "fonte": "Baseado em tabelas TACO (UNICAMP), IBGE e literatura nutricional brasileira",
      "observacoes": "Goma de tapioca hidratada na chapa com recheio salgado",
      "tags": [
        "prato feito",
        "preparação brasileira",
        "Café da Manhã / Lanche",
        "Goma de tapioca (polvilho)",
        "Queijo mussarela",
        "Presunto",
        "Manteiga"
      ],
      "ingredientes": [
        {
          "nome": "Goma de tapioca (polvilho)",
          "quantidade_g": 60
        },
        {
          "nome": "Queijo mussarela",
          "quantidade_g": 40
        },
        {
          "nome": "Presunto",
          "quantidade_g": 30
        },
        {
          "nome": "Manteiga",
          "quantidade_g": 5
        }
      ]
    },
    {
      "id": "macarrao_ao_sugo",
      "nome": "Macarrão ao Sugo",
      "categoria": "Pratos feitos brasileiros",
      "subcategoria": "Massa",
      "porcao_referencia": "350g",
      "nutrientes": {
        "energia_kcal": 380,
        "energia_kj": 1589.9,
        "carboidratos_g": 62,
        "proteinas_g": 12,
        "gorduras_totais_g": 10,
        "gorduras_saturadas_g": 1.5,
        "gorduras_trans_g": 0,
        "fibra_alimentar_g": 4,
        "acucares_totais_g": 6,
        "sodio_mg": 380,
        "colesterol_mg": null,
        "alcool_g": 0,
        "calcio_mg": 30,
        "ferro_mg": 2,
        "potassio_mg": 380,
        "vitamina_c_mg": 18,
        "vitamina_A_mcg": 55,
        "vitamina_D_mcg": 0,
        "vitamina_E_mg": 2.5,
        "vitamina_B12_mcg": 0,
        "folato_mcg": 42,
        "fosforo_mg": 140,
        "magnesio_mg": 38,
        "zinco_mg": 1,
        "selenio_mcg": 30,
        "manganes_mg": 1,
        "cobre_mg": 0.2
      },
      "fonte": "Baseado em tabelas TACO (UNICAMP), IBGE e literatura nutricional brasileira",
      "observacoes": "Espaguete com molho de tomate fresco, alho e manjericão",
      "tags": [
        "prato feito",
        "preparação brasileira",
        "Massa",
        "Espaguete cozido",
        "Tomate pelado/fresco",
        "Alho",
        "Azeite",
        "Manjericão",
        "Sal e pimenta"
      ],
      "ingredientes": [
        {
          "nome": "Espaguete cozido",
          "quantidade_g": 200
        },
        {
          "nome": "Tomate pelado/fresco",
          "quantidade_g": 100
        },
        {
          "nome": "Alho",
          "quantidade_g": 10
        },
        {
          "nome": "Azeite",
          "quantidade_g": 15
        },
        {
          "nome": "Manjericão",
          "quantidade_g": 3
        },
        {
          "nome": "Sal e pimenta",
          "quantidade_g": 3
        }
      ]
    },
    {
      "id": "carne_de_sol_com_macaxeira",
      "nome": "Carne de Sol com Macaxeira",
      "categoria": "Pratos feitos brasileiros",
      "subcategoria": "Prato Regional - Nordeste",
      "porcao_referencia": "400g",
      "nutrientes": {
        "energia_kcal": 580,
        "energia_kj": 2426.7,
        "carboidratos_g": 48,
        "proteinas_g": 40,
        "gorduras_totais_g": 24,
        "gorduras_saturadas_g": 12,
        "gorduras_trans_g": 0.5,
        "fibra_alimentar_g": 3,
        "acucares_totais_g": 2,
        "sodio_mg": 1350,
        "colesterol_mg": null,
        "alcool_g": 0,
        "calcio_mg": 38,
        "ferro_mg": 3.8,
        "potassio_mg": 760,
        "vitamina_c_mg": 25,
        "vitamina_A_mcg": 95,
        "vitamina_D_mcg": 0.2,
        "vitamina_E_mg": 1.5,
        "vitamina_B12_mcg": 3.5,
        "folato_mcg": 30,
        "fosforo_mg": 360,
        "magnesio_mg": 48,
        "zinco_mg": 6.2,
        "selenio_mcg": 28,
        "manganes_mg": 0.4,
        "cobre_mg": 0.2
      },
      "fonte": "Baseado em tabelas TACO (UNICAMP), IBGE e literatura nutricional brasileira",
      "observacoes": "Carne de sol frita ou grelhada servida com macaxeira (mandioca) cozida na manteiga",
      "tags": [
        "prato feito",
        "preparação brasileira",
        "Prato Regional - Nordeste",
        "Carne de sol",
        "Macaxeira (mandioca)",
        "Manteiga de garrafa",
        "Cebola",
        "Alho",
        "Coentro"
      ],
      "ingredientes": [
        {
          "nome": "Carne de sol",
          "quantidade_g": 180
        },
        {
          "nome": "Macaxeira (mandioca)",
          "quantidade_g": 180
        },
        {
          "nome": "Manteiga de garrafa",
          "quantidade_g": 20
        },
        {
          "nome": "Cebola",
          "quantidade_g": 20
        },
        {
          "nome": "Alho",
          "quantidade_g": 5
        },
        {
          "nome": "Coentro",
          "quantidade_g": 3
        }
      ]
    },
    {
      "id": "brigadeiro",
      "nome": "Brigadeiro",
      "categoria": "Pratos feitos brasileiros",
      "subcategoria": "Doce / Sobremesa",
      "porcao_referencia": "30g",
      "nutrientes": {
        "energia_kcal": 120,
        "energia_kj": 502.1,
        "carboidratos_g": 20,
        "proteinas_g": 2,
        "gorduras_totais_g": 4,
        "gorduras_saturadas_g": 2.5,
        "gorduras_trans_g": 0.1,
        "fibra_alimentar_g": 0.5,
        "acucares_totais_g": 18,
        "sodio_mg": 35,
        "colesterol_mg": null,
        "alcool_g": 0,
        "calcio_mg": 50,
        "ferro_mg": 0.5,
        "potassio_mg": 80,
        "vitamina_c_mg": 0.5,
        "vitamina_A_mcg": 28,
        "vitamina_D_mcg": 0.1,
        "vitamina_E_mg": 0.2,
        "vitamina_B12_mcg": 0.1,
        "folato_mcg": 3,
        "fosforo_mg": 48,
        "magnesio_mg": 8,
        "zinco_mg": 0.3,
        "selenio_mcg": 2,
        "manganes_mg": 0.05,
        "cobre_mg": 0.04
      },
      "fonte": "Baseado em tabelas TACO (UNICAMP), IBGE e literatura nutricional brasileira",
      "observacoes": "Doce de chocolate condensado enrolado em granulado, símbolo das festas brasileiras",
      "tags": [
        "prato feito",
        "preparação brasileira",
        "Doce / Sobremesa",
        "Leite condensado",
        "Chocolate em pó / cacau",
        "Manteiga",
        "Granulado de chocolate"
      ],
      "ingredientes": [
        {
          "nome": "Leite condensado",
          "quantidade_g": 18
        },
        {
          "nome": "Chocolate em pó / cacau",
          "quantidade_g": 5
        },
        {
          "nome": "Manteiga",
          "quantidade_g": 3
        },
        {
          "nome": "Granulado de chocolate",
          "quantidade_g": 4
        }
      ]
    },
    {
      "id": "frango_com_quiabo",
      "nome": "Frango com Quiabo",
      "categoria": "Pratos feitos brasileiros",
      "subcategoria": "Prato Regional - Minas Gerais",
      "porcao_referencia": "380g",
      "nutrientes": {
        "energia_kcal": 340,
        "energia_kj": 1422.6,
        "carboidratos_g": 14,
        "proteinas_g": 36,
        "gorduras_totais_g": 15,
        "gorduras_saturadas_g": 4,
        "gorduras_trans_g": 0.1,
        "fibra_alimentar_g": 6,
        "acucares_totais_g": 4,
        "sodio_mg": 420,
        "colesterol_mg": null,
        "alcool_g": 0,
        "calcio_mg": 95,
        "ferro_mg": 3.2,
        "potassio_mg": 780,
        "vitamina_c_mg": 35,
        "vitamina_A_mcg": 120,
        "vitamina_D_mcg": 0.2,
        "vitamina_E_mg": 2.2,
        "vitamina_B12_mcg": 0.5,
        "folato_mcg": 65,
        "fosforo_mg": 300,
        "magnesio_mg": 62,
        "zinco_mg": 2.4,
        "selenio_mcg": 22,
        "manganes_mg": 0.8,
        "cobre_mg": 0.25
      },
      "fonte": "Baseado em tabelas TACO (UNICAMP), IBGE e literatura nutricional brasileira",
      "observacoes": "Frango refogado com quiabo, prato típico mineiro",
      "tags": [
        "prato feito",
        "preparação brasileira",
        "Prato Regional - Minas Gerais",
        "Frango em pedaços",
        "Quiabo",
        "Tomate",
        "Cebola",
        "Alho",
        "Óleo",
        "Colorau"
      ],
      "ingredientes": [
        {
          "nome": "Frango em pedaços",
          "quantidade_g": 200
        },
        {
          "nome": "Quiabo",
          "quantidade_g": 120
        },
        {
          "nome": "Tomate",
          "quantidade_g": 40
        },
        {
          "nome": "Cebola",
          "quantidade_g": 25
        },
        {
          "nome": "Alho",
          "quantidade_g": 8
        },
        {
          "nome": "Óleo",
          "quantidade_g": 10
        },
        {
          "nome": "Colorau",
          "quantidade_g": 3
        }
      ]
    },
    {
      "id": "sopa_de_mandioca_com_frango",
      "nome": "Sopa de Mandioca com Frango",
      "categoria": "Pratos feitos brasileiros",
      "subcategoria": "Sopa",
      "porcao_referencia": "400g",
      "nutrientes": {
        "energia_kcal": 340,
        "energia_kj": 1422.6,
        "carboidratos_g": 44,
        "proteinas_g": 22,
        "gorduras_totais_g": 8,
        "gorduras_saturadas_g": 2,
        "gorduras_trans_g": 0,
        "fibra_alimentar_g": 3,
        "acucares_totais_g": 3,
        "sodio_mg": 560,
        "colesterol_mg": null,
        "alcool_g": 0,
        "calcio_mg": 35,
        "ferro_mg": 2.2,
        "potassio_mg": 640,
        "vitamina_c_mg": 22,
        "vitamina_A_mcg": 20,
        "vitamina_D_mcg": 0.1,
        "vitamina_E_mg": 1,
        "vitamina_B12_mcg": 0.3,
        "folato_mcg": 28,
        "fosforo_mg": 240,
        "magnesio_mg": 40,
        "zinco_mg": 1.6,
        "selenio_mcg": 14,
        "manganes_mg": 0.5,
        "cobre_mg": 0.2
      },
      "fonte": "Baseado em tabelas TACO (UNICAMP), IBGE e literatura nutricional brasileira",
      "observacoes": "Caldo cremoso de mandioca com pedaços de frango desfiado e cheiro-verde",
      "tags": [
        "prato feito",
        "preparação brasileira",
        "Sopa",
        "Mandioca cozida",
        "Frango desfiado",
        "Caldo de frango",
        "Cebola",
        "Alho",
        "Cheiro-verde",
        "Sal e temperos"
      ],
      "ingredientes": [
        {
          "nome": "Mandioca cozida",
          "quantidade_g": 180
        },
        {
          "nome": "Frango desfiado",
          "quantidade_g": 100
        },
        {
          "nome": "Caldo de frango",
          "quantidade_g": 80
        },
        {
          "nome": "Cebola",
          "quantidade_g": 20
        },
        {
          "nome": "Alho",
          "quantidade_g": 8
        },
        {
          "nome": "Cheiro-verde",
          "quantidade_g": 5
        },
        {
          "nome": "Sal e temperos",
          "quantidade_g": 4
        }
      ]
    },
    {
      "id": "rabada_com_agriao",
      "nome": "Rabada com Agrião",
      "categoria": "Pratos feitos brasileiros",
      "subcategoria": "Prato de Vísceras / Tradicional",
      "porcao_referencia": "350g",
      "nutrientes": {
        "energia_kcal": 490,
        "energia_kj": 2050.2,
        "carboidratos_g": 6,
        "proteinas_g": 45,
        "gorduras_totais_g": 30,
        "gorduras_saturadas_g": 12,
        "gorduras_trans_g": 0.8,
        "fibra_alimentar_g": 2,
        "acucares_totais_g": 3,
        "sodio_mg": 680,
        "colesterol_mg": null,
        "alcool_g": 0,
        "calcio_mg": 75,
        "ferro_mg": 4.8,
        "potassio_mg": 420,
        "vitamina_c_mg": 22,
        "vitamina_A_mcg": 95,
        "vitamina_D_mcg": 0.1,
        "vitamina_E_mg": 1.8,
        "vitamina_B12_mcg": 5.5,
        "folato_mcg": 22,
        "fosforo_mg": 280,
        "magnesio_mg": 28,
        "zinco_mg": 7.5,
        "selenio_mcg": 22,
        "manganes_mg": 0.3,
        "cobre_mg": 0.25
      },
      "fonte": "Baseado em tabelas TACO (UNICAMP), IBGE e literatura nutricional brasileira",
      "observacoes": "Rabo bovino cozido lentamente com temperos, servido com agrião fresco",
      "tags": [
        "prato feito",
        "preparação brasileira",
        "Prato de Vísceras / Tradicional",
        "Rabo bovino",
        "Agrião",
        "Tomate",
        "Cebola",
        "Alho",
        "Vinho tinto seco",
        "Sal e pimenta"
      ],
      "ingredientes": [
        {
          "nome": "Rabo bovino",
          "quantidade_g": 250
        },
        {
          "nome": "Agrião",
          "quantidade_g": 50
        },
        {
          "nome": "Tomate",
          "quantidade_g": 30
        },
        {
          "nome": "Cebola",
          "quantidade_g": 20
        },
        {
          "nome": "Alho",
          "quantidade_g": 8
        },
        {
          "nome": "Vinho tinto seco",
          "quantidade_g": 20
        },
        {
          "nome": "Sal e pimenta",
          "quantidade_g": 4
        }
      ]
    },
    {
      "id": "arroz_de_carreteiro",
      "nome": "Arroz de Carreteiro",
      "categoria": "Pratos feitos brasileiros",
      "subcategoria": "Prato Regional - Sul",
      "porcao_referencia": "380g",
      "nutrientes": {
        "energia_kcal": 530,
        "energia_kj": 2217.5,
        "carboidratos_g": 55,
        "proteinas_g": 38,
        "gorduras_totais_g": 16,
        "gorduras_saturadas_g": 5.5,
        "gorduras_trans_g": 0.2,
        "fibra_alimentar_g": 2,
        "acucares_totais_g": 2,
        "sodio_mg": 1180,
        "colesterol_mg": null,
        "alcool_g": 0,
        "calcio_mg": 28,
        "ferro_mg": 3.8,
        "potassio_mg": 580,
        "vitamina_c_mg": 8,
        "vitamina_A_mcg": 25,
        "vitamina_D_mcg": 0.2,
        "vitamina_E_mg": 1.2,
        "vitamina_B12_mcg": 2.8,
        "folato_mcg": 22,
        "fosforo_mg": 320,
        "magnesio_mg": 45,
        "zinco_mg": 5.5,
        "selenio_mcg": 24,
        "manganes_mg": 0.8,
        "cobre_mg": 0.2
      },
      "fonte": "Baseado em tabelas TACO (UNICAMP), IBGE e literatura nutricional brasileira",
      "observacoes": "Arroz cozido com carne seca desfiada e bacon, prato gaúcho tradicional",
      "tags": [
        "prato feito",
        "preparação brasileira",
        "Prato Regional - Sul",
        "Arroz branco",
        "Carne seca",
        "Bacon",
        "Cebola",
        "Alho",
        "Tomate",
        "Cheiro-verde"
      ],
      "ingredientes": [
        {
          "nome": "Arroz branco",
          "quantidade_g": 150
        },
        {
          "nome": "Carne seca",
          "quantidade_g": 120
        },
        {
          "nome": "Bacon",
          "quantidade_g": 30
        },
        {
          "nome": "Cebola",
          "quantidade_g": 25
        },
        {
          "nome": "Alho",
          "quantidade_g": 8
        },
        {
          "nome": "Tomate",
          "quantidade_g": 30
        },
        {
          "nome": "Cheiro-verde",
          "quantidade_g": 5
        }
      ]
    },
    {
      "id": "acai_na_tigela",
      "nome": "Açaí na Tigela",
      "categoria": "Pratos feitos brasileiros",
      "subcategoria": "Lanche / Esporte",
      "porcao_referencia": "300g",
      "nutrientes": {
        "energia_kcal": 420,
        "energia_kj": 1757.3,
        "carboidratos_g": 62,
        "proteinas_g": 6,
        "gorduras_totais_g": 16,
        "gorduras_saturadas_g": 5,
        "gorduras_trans_g": 0,
        "fibra_alimentar_g": 8,
        "acucares_totais_g": 38,
        "sodio_mg": 40,
        "colesterol_mg": null,
        "alcool_g": 0,
        "calcio_mg": 45,
        "ferro_mg": 3.5,
        "potassio_mg": 580,
        "vitamina_c_mg": 10,
        "vitamina_A_mcg": 15,
        "vitamina_D_mcg": 0,
        "vitamina_E_mg": 8.5,
        "vitamina_B12_mcg": 0,
        "folato_mcg": 30,
        "fosforo_mg": 120,
        "magnesio_mg": 48,
        "zinco_mg": 1.2,
        "selenio_mcg": 4,
        "manganes_mg": 2.8,
        "cobre_mg": 0.5
      },
      "fonte": "Baseado em tabelas TACO (UNICAMP), IBGE e literatura nutricional brasileira",
      "observacoes": "Polpa de açaí batida com guaraná e servida com granola, banana e mel",
      "tags": [
        "prato feito",
        "preparação brasileira",
        "Lanche / Esporte",
        "Polpa de açaí",
        "Xarope de guaraná",
        "Granola",
        "Banana",
        "Mel"
      ],
      "ingredientes": [
        {
          "nome": "Polpa de açaí",
          "quantidade_g": 200
        },
        {
          "nome": "Xarope de guaraná",
          "quantidade_g": 20
        },
        {
          "nome": "Granola",
          "quantidade_g": 40
        },
        {
          "nome": "Banana",
          "quantidade_g": 60
        },
        {
          "nome": "Mel",
          "quantidade_g": 10
        }
      ]
    },
    {
      "id": "bife_a_parmegiana_com_arroz_e_batata",
      "nome": "Bife à Parmegiana com Arroz e Batata",
      "categoria": "Pratos feitos brasileiros",
      "subcategoria": "Prato executivo / Restaurante",
      "porcao_referencia": "520g",
      "nutrientes": {
        "energia_kcal": 920,
        "energia_kj": 3849.3,
        "carboidratos_g": 82,
        "proteinas_g": 47,
        "gorduras_totais_g": 45,
        "gorduras_saturadas_g": 15,
        "gorduras_trans_g": 0.8,
        "fibra_alimentar_g": 5,
        "acucares_totais_g": 6,
        "sodio_mg": 1380,
        "colesterol_mg": null,
        "alcool_g": 0,
        "calcio_mg": 310,
        "ferro_mg": 5.2,
        "potassio_mg": 980,
        "vitamina_c_mg": 18,
        "vitamina_A_mcg": 110,
        "vitamina_D_mcg": 0.4,
        "vitamina_E_mg": 4.2,
        "vitamina_B12_mcg": 3.2,
        "folato_mcg": 80,
        "fosforo_mg": 560,
        "magnesio_mg": 82,
        "zinco_mg": 7.2,
        "selenio_mcg": 20,
        "manganes_mg": 1.2,
        "cobre_mg": 0.35
      },
      "fonte": "Baseado em tabelas TACO (UNICAMP), IBGE e literatura nutricional brasileira",
      "observacoes": "Bife bovino empanado com molho de tomate e queijo mussarela, servido com arroz branco e batata frita.",
      "tags": [
        "prato feito",
        "preparação brasileira",
        "Prato executivo / Restaurante",
        "parmegiana",
        "bife à parmegiana",
        "mussarela",
        "executivo",
        "Bife bovino empanado",
        "Molho de tomate",
        "Queijo mussarela",
        "Arroz branco cozido",
        "Batata frita",
        "Óleo de fritura absorvido",
        "Sal e temperos"
      ],
      "ingredientes": [
        {
          "nome": "Bife bovino empanado",
          "quantidade_g": 180
        },
        {
          "nome": "Molho de tomate",
          "quantidade_g": 80
        },
        {
          "nome": "Queijo mussarela",
          "quantidade_g": 45
        },
        {
          "nome": "Arroz branco cozido",
          "quantidade_g": 160
        },
        {
          "nome": "Batata frita",
          "quantidade_g": 120
        },
        {
          "nome": "Óleo de fritura absorvido",
          "quantidade_g": 20
        },
        {
          "nome": "Sal e temperos",
          "quantidade_g": 5
        }
      ]
    },
    {
      "id": "frango_a_parmegiana_com_arroz_e_pure",
      "nome": "Frango à Parmegiana com Arroz e Purê",
      "categoria": "Pratos feitos brasileiros",
      "subcategoria": "Prato executivo / Restaurante",
      "porcao_referencia": "500g",
      "nutrientes": {
        "energia_kcal": 820,
        "energia_kj": 3430.9,
        "carboidratos_g": 76,
        "proteinas_g": 48,
        "gorduras_totais_g": 34,
        "gorduras_saturadas_g": 11,
        "gorduras_trans_g": 0.5,
        "fibra_alimentar_g": 4.5,
        "acucares_totais_g": 6,
        "sodio_mg": 1250,
        "colesterol_mg": null,
        "alcool_g": 0,
        "calcio_mg": 270,
        "ferro_mg": 3.2,
        "potassio_mg": 900,
        "vitamina_c_mg": 16,
        "vitamina_A_mcg": 95,
        "vitamina_D_mcg": 0.3,
        "vitamina_E_mg": 3.5,
        "vitamina_B12_mcg": 1.6,
        "folato_mcg": 72,
        "fosforo_mg": 520,
        "magnesio_mg": 76,
        "zinco_mg": 3.8,
        "selenio_mcg": 20,
        "manganes_mg": 1,
        "cobre_mg": 0.3
      },
      "fonte": "Baseado em tabelas TACO (UNICAMP), IBGE e literatura nutricional brasileira",
      "observacoes": "Filé de frango empanado com molho de tomate e queijo mussarela, servido com arroz branco e purê de batata.",
      "tags": [
        "prato feito",
        "preparação brasileira",
        "Prato executivo / Restaurante",
        "parmegiana",
        "frango à parmegiana",
        "mussarela",
        "executivo",
        "Filé de frango empanado",
        "Molho de tomate",
        "Queijo mussarela",
        "Arroz branco cozido",
        "Purê de batata",
        "Óleo de fritura absorvido",
        "Sal e temperos"
      ],
      "ingredientes": [
        {
          "nome": "Filé de frango empanado",
          "quantidade_g": 180
        },
        {
          "nome": "Molho de tomate",
          "quantidade_g": 80
        },
        {
          "nome": "Queijo mussarela",
          "quantidade_g": 40
        },
        {
          "nome": "Arroz branco cozido",
          "quantidade_g": 150
        },
        {
          "nome": "Purê de batata",
          "quantidade_g": 120
        },
        {
          "nome": "Óleo de fritura absorvido",
          "quantidade_g": 18
        },
        {
          "nome": "Sal e temperos",
          "quantidade_g": 5
        }
      ]
    },
    {
      "id": "bife_acebolado_com_arroz_feijao_e_fritas",
      "nome": "Bife Acebolado com Arroz, Feijão e Fritas",
      "categoria": "Pratos feitos brasileiros",
      "subcategoria": "Prato feito clássico",
      "porcao_referencia": "520g",
      "nutrientes": {
        "energia_kcal": 850,
        "energia_kj": 3556.4,
        "carboidratos_g": 88,
        "proteinas_g": 43,
        "gorduras_totais_g": 36,
        "gorduras_saturadas_g": 11,
        "gorduras_trans_g": 0.5,
        "fibra_alimentar_g": 11,
        "acucares_totais_g": 4,
        "sodio_mg": 1120,
        "colesterol_mg": null,
        "alcool_g": 0,
        "calcio_mg": 95,
        "ferro_mg": 6.3,
        "potassio_mg": 1150,
        "vitamina_c_mg": 18,
        "vitamina_A_mcg": 20,
        "vitamina_D_mcg": 0.2,
        "vitamina_E_mg": 3.3,
        "vitamina_B12_mcg": 3.8,
        "folato_mcg": 190,
        "fosforo_mg": 520,
        "magnesio_mg": 120,
        "zinco_mg": 7.4,
        "selenio_mcg": 20,
        "manganes_mg": 1.6,
        "cobre_mg": 0.55
      },
      "fonte": "Baseado em tabelas TACO (UNICAMP), IBGE e literatura nutricional brasileira",
      "observacoes": "Prato feito comum de restaurante com bife bovino acebolado, arroz, feijão carioca e batata frita.",
      "tags": [
        "prato feito",
        "preparação brasileira",
        "Prato feito clássico",
        "pf",
        "bife acebolado",
        "arroz e feijão",
        "marmitex",
        "Bife bovino grelhado",
        "Cebola refogada",
        "Arroz branco cozido",
        "Feijão carioca cozido",
        "Batata frita",
        "Óleo",
        "Sal e temperos"
      ],
      "ingredientes": [
        {
          "nome": "Bife bovino grelhado",
          "quantidade_g": 160
        },
        {
          "nome": "Cebola refogada",
          "quantidade_g": 45
        },
        {
          "nome": "Arroz branco cozido",
          "quantidade_g": 160
        },
        {
          "nome": "Feijão carioca cozido",
          "quantidade_g": 130
        },
        {
          "nome": "Batata frita",
          "quantidade_g": 100
        },
        {
          "nome": "Óleo",
          "quantidade_g": 15
        },
        {
          "nome": "Sal e temperos",
          "quantidade_g": 5
        }
      ]
    },
    {
      "id": "frango_grelhado_com_arroz_feijao_e_saladas",
      "nome": "Frango Grelhado com Arroz, Feijão e Saladas",
      "categoria": "Pratos feitos brasileiros",
      "subcategoria": "Prato feito leve",
      "porcao_referencia": "480g",
      "nutrientes": {
        "energia_kcal": 610,
        "energia_kj": 2552.2,
        "carboidratos_g": 72,
        "proteinas_g": 47,
        "gorduras_totais_g": 15,
        "gorduras_saturadas_g": 3.5,
        "gorduras_trans_g": 0.1,
        "fibra_alimentar_g": 12,
        "acucares_totais_g": 6,
        "sodio_mg": 860,
        "colesterol_mg": null,
        "alcool_g": 0,
        "calcio_mg": 110,
        "ferro_mg": 4.8,
        "potassio_mg": 1150,
        "vitamina_c_mg": 28,
        "vitamina_A_mcg": 380,
        "vitamina_D_mcg": 0.2,
        "vitamina_E_mg": 2.4,
        "vitamina_B12_mcg": 0.8,
        "folato_mcg": 185,
        "fosforo_mg": 480,
        "magnesio_mg": 115,
        "zinco_mg": 3.2,
        "selenio_mcg": 20,
        "manganes_mg": 1.3,
        "cobre_mg": 0.45
      },
      "fonte": "Baseado em tabelas TACO (UNICAMP), IBGE e literatura nutricional brasileira",
      "observacoes": "Prato executivo comum com filé de frango grelhado, arroz, feijão e saladas simples.",
      "tags": [
        "prato feito",
        "preparação brasileira",
        "Prato feito leve",
        "pf",
        "frango grelhado",
        "arroz e feijão",
        "salada",
        "executivo",
        "Filé de frango grelhado",
        "Arroz branco cozido",
        "Feijão carioca cozido",
        "Alface",
        "Tomate",
        "Cenoura ralada",
        "Óleo ou azeite",
        "Sal e temperos"
      ],
      "ingredientes": [
        {
          "nome": "Filé de frango grelhado",
          "quantidade_g": 160
        },
        {
          "nome": "Arroz branco cozido",
          "quantidade_g": 150
        },
        {
          "nome": "Feijão carioca cozido",
          "quantidade_g": 120
        },
        {
          "nome": "Alface",
          "quantidade_g": 30
        },
        {
          "nome": "Tomate",
          "quantidade_g": 50
        },
        {
          "nome": "Cenoura ralada",
          "quantidade_g": 40
        },
        {
          "nome": "Óleo ou azeite",
          "quantidade_g": 8
        },
        {
          "nome": "Sal e temperos",
          "quantidade_g": 4
        }
      ]
    },
    {
      "id": "frango_a_milanesa_com_arroz_e_feijao",
      "nome": "Frango à Milanesa com Arroz e Feijão",
      "categoria": "Pratos feitos brasileiros",
      "subcategoria": "Prato feito clássico",
      "porcao_referencia": "480g",
      "nutrientes": {
        "energia_kcal": 760,
        "energia_kj": 3179.8,
        "carboidratos_g": 82,
        "proteinas_g": 48,
        "gorduras_totais_g": 27,
        "gorduras_saturadas_g": 5.5,
        "gorduras_trans_g": 0.3,
        "fibra_alimentar_g": 10,
        "acucares_totais_g": 3,
        "sodio_mg": 980,
        "colesterol_mg": null,
        "alcool_g": 0,
        "calcio_mg": 90,
        "ferro_mg": 4.5,
        "potassio_mg": 920,
        "vitamina_c_mg": 3,
        "vitamina_A_mcg": 60,
        "vitamina_D_mcg": 0.6,
        "vitamina_E_mg": 3,
        "vitamina_B12_mcg": 1.2,
        "folato_mcg": 165,
        "fosforo_mg": 520,
        "magnesio_mg": 105,
        "zinco_mg": 3.5,
        "selenio_mcg": 20,
        "manganes_mg": 1.4,
        "cobre_mg": 0.4
      },
      "fonte": "Baseado em tabelas TACO (UNICAMP), IBGE e literatura nutricional brasileira",
      "observacoes": "Filé de frango empanado e frito, servido com arroz branco e feijão.",
      "tags": [
        "prato feito",
        "preparação brasileira",
        "Prato feito clássico",
        "pf",
        "frango à milanesa",
        "empanado",
        "arroz e feijão",
        "Filé de frango empanado",
        "Arroz branco cozido",
        "Feijão carioca cozido",
        "Óleo de fritura absorvido",
        "Farinha de rosca",
        "Ovo",
        "Sal e temperos"
      ],
      "ingredientes": [
        {
          "nome": "Filé de frango empanado",
          "quantidade_g": 180
        },
        {
          "nome": "Arroz branco cozido",
          "quantidade_g": 160
        },
        {
          "nome": "Feijão carioca cozido",
          "quantidade_g": 130
        },
        {
          "nome": "Óleo de fritura absorvido",
          "quantidade_g": 20
        },
        {
          "nome": "Farinha de rosca",
          "quantidade_g": 25
        },
        {
          "nome": "Ovo",
          "quantidade_g": 25
        },
        {
          "nome": "Sal e temperos",
          "quantidade_g": 5
        }
      ]
    },
    {
      "id": "carne_de_panela_com_batata_arroz_e_feijao",
      "nome": "Carne de Panela com Batata, Arroz e Feijão",
      "categoria": "Pratos feitos brasileiros",
      "subcategoria": "Prato feito caseiro",
      "porcao_referencia": "520g",
      "nutrientes": {
        "energia_kcal": 720,
        "energia_kj": 3012.5,
        "carboidratos_g": 78,
        "proteinas_g": 45,
        "gorduras_totais_g": 25,
        "gorduras_saturadas_g": 8,
        "gorduras_trans_g": 0.5,
        "fibra_alimentar_g": 12,
        "acucares_totais_g": 5,
        "sodio_mg": 1050,
        "colesterol_mg": null,
        "alcool_g": 0,
        "calcio_mg": 105,
        "ferro_mg": 6.2,
        "potassio_mg": 1350,
        "vitamina_c_mg": 22,
        "vitamina_A_mcg": 90,
        "vitamina_D_mcg": 0.2,
        "vitamina_E_mg": 2,
        "vitamina_B12_mcg": 3.8,
        "folato_mcg": 180,
        "fosforo_mg": 520,
        "magnesio_mg": 120,
        "zinco_mg": 7,
        "selenio_mcg": 20,
        "manganes_mg": 1.4,
        "cobre_mg": 0.5
      },
      "fonte": "Baseado em tabelas TACO (UNICAMP), IBGE e literatura nutricional brasileira",
      "observacoes": "Carne bovina cozida com batata e molho, servida com arroz branco e feijão.",
      "tags": [
        "prato feito",
        "preparação brasileira",
        "Prato feito caseiro",
        "pf",
        "carne de panela",
        "arroz e feijão",
        "comida caseira",
        "Carne bovina cozida",
        "Batata cozida",
        "Molho de tomate e legumes",
        "Arroz branco cozido",
        "Feijão carioca cozido",
        "Óleo",
        "Sal e temperos"
      ],
      "ingredientes": [
        {
          "nome": "Carne bovina cozida",
          "quantidade_g": 170
        },
        {
          "nome": "Batata cozida",
          "quantidade_g": 100
        },
        {
          "nome": "Molho de tomate e legumes",
          "quantidade_g": 80
        },
        {
          "nome": "Arroz branco cozido",
          "quantidade_g": 140
        },
        {
          "nome": "Feijão carioca cozido",
          "quantidade_g": 120
        },
        {
          "nome": "Óleo",
          "quantidade_g": 10
        },
        {
          "nome": "Sal e temperos",
          "quantidade_g": 5
        }
      ]
    },
    {
      "id": "picadinho_de_carne_com_arroz_feijao_e_farofa",
      "nome": "Picadinho de Carne com Arroz, Feijão e Farofa",
      "categoria": "Pratos feitos brasileiros",
      "subcategoria": "Prato executivo / Restaurante",
      "porcao_referencia": "500g",
      "nutrientes": {
        "energia_kcal": 790,
        "energia_kj": 3305.4,
        "carboidratos_g": 86,
        "proteinas_g": 42,
        "gorduras_totais_g": 32,
        "gorduras_saturadas_g": 9,
        "gorduras_trans_g": 0.5,
        "fibra_alimentar_g": 11,
        "acucares_totais_g": 4,
        "sodio_mg": 1180,
        "colesterol_mg": null,
        "alcool_g": 0,
        "calcio_mg": 95,
        "ferro_mg": 6,
        "potassio_mg": 1050,
        "vitamina_c_mg": 9,
        "vitamina_A_mcg": 50,
        "vitamina_D_mcg": 0.2,
        "vitamina_E_mg": 2.5,
        "vitamina_B12_mcg": 3.5,
        "folato_mcg": 175,
        "fosforo_mg": 500,
        "magnesio_mg": 115,
        "zinco_mg": 6.8,
        "selenio_mcg": 20,
        "manganes_mg": 1.8,
        "cobre_mg": 0.5
      },
      "fonte": "Baseado em tabelas TACO (UNICAMP), IBGE e literatura nutricional brasileira",
      "observacoes": "Picadinho bovino ao molho, servido com arroz, feijão e farofa.",
      "tags": [
        "prato feito",
        "preparação brasileira",
        "Prato executivo / Restaurante",
        "pf",
        "picadinho",
        "executivo",
        "arroz e feijão",
        "Carne bovina em cubos",
        "Molho do picadinho",
        "Arroz branco cozido",
        "Feijão carioca cozido",
        "Farofa pronta",
        "Óleo",
        "Sal e temperos"
      ],
      "ingredientes": [
        {
          "nome": "Carne bovina em cubos",
          "quantidade_g": 160
        },
        {
          "nome": "Molho do picadinho",
          "quantidade_g": 70
        },
        {
          "nome": "Arroz branco cozido",
          "quantidade_g": 150
        },
        {
          "nome": "Feijão carioca cozido",
          "quantidade_g": 120
        },
        {
          "nome": "Farofa pronta",
          "quantidade_g": 50
        },
        {
          "nome": "Óleo",
          "quantidade_g": 12
        },
        {
          "nome": "Sal e temperos",
          "quantidade_g": 5
        }
      ]
    },
    {
      "id": "feijao_tropeiro_com_bisteca_e_couve",
      "nome": "Feijão Tropeiro com Bisteca e Couve",
      "categoria": "Pratos feitos brasileiros",
      "subcategoria": "Prato regional - Minas Gerais",
      "porcao_referencia": "480g",
      "nutrientes": {
        "energia_kcal": 930,
        "energia_kj": 3891.1,
        "carboidratos_g": 58,
        "proteinas_g": 55,
        "gorduras_totais_g": 54,
        "gorduras_saturadas_g": 18,
        "gorduras_trans_g": 0.7,
        "fibra_alimentar_g": 16,
        "acucares_totais_g": 4,
        "sodio_mg": 1650,
        "colesterol_mg": null,
        "alcool_g": 0,
        "calcio_mg": 170,
        "ferro_mg": 7.2,
        "potassio_mg": 1200,
        "vitamina_c_mg": 36,
        "vitamina_A_mcg": 260,
        "vitamina_D_mcg": 1.2,
        "vitamina_E_mg": 3.2,
        "vitamina_B12_mcg": 2.4,
        "folato_mcg": 210,
        "fosforo_mg": 680,
        "magnesio_mg": 145,
        "zinco_mg": 6.5,
        "selenio_mcg": 20,
        "manganes_mg": 1.4,
        "cobre_mg": 0.55
      },
      "fonte": "Baseado em tabelas TACO (UNICAMP), IBGE e literatura nutricional brasileira",
      "observacoes": "Feijão tropeiro com farinha, ovos, linguiça e bacon, servido com bisteca suína e couve refogada.",
      "tags": [
        "prato feito",
        "preparação brasileira",
        "Prato regional - Minas Gerais",
        "feijão tropeiro",
        "tropeiro",
        "bisteca",
        "minas gerais",
        "Feijão cozido",
        "Farinha de mandioca",
        "Linguiça calabresa",
        "Bacon",
        "Ovo",
        "Bisteca suína grelhada",
        "Couve refogada",
        "Alho, cebola e temperos"
      ],
      "ingredientes": [
        {
          "nome": "Feijão cozido",
          "quantidade_g": 150
        },
        {
          "nome": "Farinha de mandioca",
          "quantidade_g": 50
        },
        {
          "nome": "Linguiça calabresa",
          "quantidade_g": 50
        },
        {
          "nome": "Bacon",
          "quantidade_g": 35
        },
        {
          "nome": "Ovo",
          "quantidade_g": 50
        },
        {
          "nome": "Bisteca suína grelhada",
          "quantidade_g": 140
        },
        {
          "nome": "Couve refogada",
          "quantidade_g": 55
        },
        {
          "nome": "Alho, cebola e temperos",
          "quantidade_g": 10
        }
      ]
    },
    {
      "id": "peixe_grelhado_com_arroz_pirao_e_legumes",
      "nome": "Peixe Grelhado com Arroz, Pirão e Legumes",
      "categoria": "Pratos feitos brasileiros",
      "subcategoria": "Prato de peixe / Restaurante",
      "porcao_referencia": "460g",
      "nutrientes": {
        "energia_kcal": 560,
        "energia_kj": 2343,
        "carboidratos_g": 62,
        "proteinas_g": 42,
        "gorduras_totais_g": 16,
        "gorduras_saturadas_g": 3.2,
        "gorduras_trans_g": 0.1,
        "fibra_alimentar_g": 5.5,
        "acucares_totais_g": 4,
        "sodio_mg": 850,
        "colesterol_mg": null,
        "alcool_g": 0,
        "calcio_mg": 85,
        "ferro_mg": 2.2,
        "potassio_mg": 920,
        "vitamina_c_mg": 24,
        "vitamina_A_mcg": 240,
        "vitamina_D_mcg": 2.5,
        "vitamina_E_mg": 2.3,
        "vitamina_B12_mcg": 3.2,
        "folato_mcg": 75,
        "fosforo_mg": 540,
        "magnesio_mg": 95,
        "zinco_mg": 2.2,
        "selenio_mcg": 20,
        "manganes_mg": 1,
        "cobre_mg": 0.25
      },
      "fonte": "Baseado em tabelas TACO (UNICAMP), IBGE e literatura nutricional brasileira",
      "observacoes": "Filé de peixe grelhado servido com arroz branco, pirão leve e legumes cozidos.",
      "tags": [
        "prato feito",
        "preparação brasileira",
        "Prato de peixe / Restaurante",
        "peixe grelhado",
        "pirão",
        "executivo",
        "legumes",
        "Filé de peixe grelhado",
        "Arroz branco cozido",
        "Pirão",
        "Legumes cozidos",
        "Óleo ou azeite",
        "Limão e temperos"
      ],
      "ingredientes": [
        {
          "nome": "Filé de peixe grelhado",
          "quantidade_g": 180
        },
        {
          "nome": "Arroz branco cozido",
          "quantidade_g": 130
        },
        {
          "nome": "Pirão",
          "quantidade_g": 90
        },
        {
          "nome": "Legumes cozidos",
          "quantidade_g": 80
        },
        {
          "nome": "Óleo ou azeite",
          "quantidade_g": 10
        },
        {
          "nome": "Limão e temperos",
          "quantidade_g": 8
        }
      ]
    },
    {
      "id": "bobo_de_camarao_com_arroz",
      "nome": "Bobó de Camarão com Arroz",
      "categoria": "Pratos feitos brasileiros",
      "subcategoria": "Prato regional - Bahia",
      "porcao_referencia": "420g",
      "nutrientes": {
        "energia_kcal": 690,
        "energia_kj": 2887,
        "carboidratos_g": 78,
        "proteinas_g": 34,
        "gorduras_totais_g": 28,
        "gorduras_saturadas_g": 13,
        "gorduras_trans_g": 0.1,
        "fibra_alimentar_g": 6,
        "acucares_totais_g": 5,
        "sodio_mg": 980,
        "colesterol_mg": null,
        "alcool_g": 0,
        "calcio_mg": 135,
        "ferro_mg": 3.4,
        "potassio_mg": 850,
        "vitamina_c_mg": 24,
        "vitamina_A_mcg": 180,
        "vitamina_D_mcg": 0.4,
        "vitamina_E_mg": 5.5,
        "vitamina_B12_mcg": 2.2,
        "folato_mcg": 90,
        "fosforo_mg": 420,
        "magnesio_mg": 95,
        "zinco_mg": 3.2,
        "selenio_mcg": 20,
        "manganes_mg": 1.2,
        "cobre_mg": 0.7
      },
      "fonte": "Baseado em tabelas TACO (UNICAMP), IBGE e literatura nutricional brasileira",
      "observacoes": "Bobó de camarão com mandioca, leite de coco e dendê, servido com arroz branco.",
      "tags": [
        "prato feito",
        "preparação brasileira",
        "Prato regional - Bahia",
        "bobó de camarão",
        "camarão",
        "bahia",
        "dendê",
        "Camarão cozido",
        "Mandioca cozida e batida",
        "Leite de coco",
        "Azeite de dendê",
        "Arroz branco cozido",
        "Tomate, cebola e pimentão",
        "Coentro e temperos"
      ],
      "ingredientes": [
        {
          "nome": "Camarão cozido",
          "quantidade_g": 120
        },
        {
          "nome": "Mandioca cozida e batida",
          "quantidade_g": 150
        },
        {
          "nome": "Leite de coco",
          "quantidade_g": 60
        },
        {
          "nome": "Azeite de dendê",
          "quantidade_g": 15
        },
        {
          "nome": "Arroz branco cozido",
          "quantidade_g": 130
        },
        {
          "nome": "Tomate, cebola e pimentão",
          "quantidade_g": 55
        },
        {
          "nome": "Coentro e temperos",
          "quantidade_g": 8
        }
      ]
    },
    {
      "id": "dobradinha_com_feijao_branco_e_arroz",
      "nome": "Dobradinha com Feijão Branco e Arroz",
      "categoria": "Pratos feitos brasileiros",
      "subcategoria": "Prato tradicional / Restaurante",
      "porcao_referencia": "480g",
      "nutrientes": {
        "energia_kcal": 710,
        "energia_kj": 2970.6,
        "carboidratos_g": 70,
        "proteinas_g": 50,
        "gorduras_totais_g": 26,
        "gorduras_saturadas_g": 9,
        "gorduras_trans_g": 0.4,
        "fibra_alimentar_g": 14,
        "acucares_totais_g": 5,
        "sodio_mg": 1450,
        "colesterol_mg": null,
        "alcool_g": 0,
        "calcio_mg": 140,
        "ferro_mg": 6.8,
        "potassio_mg": 1180,
        "vitamina_c_mg": 16,
        "vitamina_A_mcg": 55,
        "vitamina_D_mcg": 0.2,
        "vitamina_E_mg": 1.8,
        "vitamina_B12_mcg": 2.8,
        "folato_mcg": 170,
        "fosforo_mg": 560,
        "magnesio_mg": 135,
        "zinco_mg": 5,
        "selenio_mcg": 20,
        "manganes_mg": 1.1,
        "cobre_mg": 0.5
      },
      "fonte": "Baseado em tabelas TACO (UNICAMP), IBGE e literatura nutricional brasileira",
      "observacoes": "Dobradinha bovina cozida com feijão branco, linguiça e temperos, servida com arroz branco.",
      "tags": [
        "prato feito",
        "preparação brasileira",
        "Prato tradicional / Restaurante",
        "dobradinha",
        "bucho",
        "feijão branco",
        "prato do dia",
        "Dobradinha bovina cozida",
        "Feijão branco cozido",
        "Linguiça calabresa",
        "Arroz branco cozido",
        "Tomate, cebola e alho",
        "Óleo",
        "Sal e temperos"
      ],
      "ingredientes": [
        {
          "nome": "Dobradinha bovina cozida",
          "quantidade_g": 180
        },
        {
          "nome": "Feijão branco cozido",
          "quantidade_g": 150
        },
        {
          "nome": "Linguiça calabresa",
          "quantidade_g": 45
        },
        {
          "nome": "Arroz branco cozido",
          "quantidade_g": 120
        },
        {
          "nome": "Tomate, cebola e alho",
          "quantidade_g": 55
        },
        {
          "nome": "Óleo",
          "quantidade_g": 8
        },
        {
          "nome": "Sal e temperos",
          "quantidade_g": 5
        }
      ]
    },
    {
      "id": "caldo_verde_com_linguica",
      "nome": "Caldo Verde com Linguiça",
      "categoria": "Pratos feitos brasileiros",
      "subcategoria": "Sopa / Caldo",
      "porcao_referencia": "350g",
      "nutrientes": {
        "energia_kcal": 430,
        "energia_kj": 1799.1,
        "carboidratos_g": 42,
        "proteinas_g": 15,
        "gorduras_totais_g": 23,
        "gorduras_saturadas_g": 7,
        "gorduras_trans_g": 0.3,
        "fibra_alimentar_g": 6,
        "acucares_totais_g": 4,
        "sodio_mg": 1080,
        "colesterol_mg": null,
        "alcool_g": 0,
        "calcio_mg": 95,
        "ferro_mg": 2.6,
        "potassio_mg": 850,
        "vitamina_c_mg": 42,
        "vitamina_A_mcg": 250,
        "vitamina_D_mcg": 0.1,
        "vitamina_E_mg": 2.2,
        "vitamina_B12_mcg": 0.8,
        "folato_mcg": 85,
        "fosforo_mg": 220,
        "magnesio_mg": 65,
        "zinco_mg": 2,
        "selenio_mcg": 20,
        "manganes_mg": 0.8,
        "cobre_mg": 0.3
      },
      "fonte": "Baseado em tabelas TACO (UNICAMP), IBGE e literatura nutricional brasileira",
      "observacoes": "Caldo de batata com couve fatiada e linguiça, comum em restaurantes e padarias.",
      "tags": [
        "prato feito",
        "preparação brasileira",
        "Sopa / Caldo",
        "caldo verde",
        "sopa",
        "caldo",
        "linguiça",
        "Batata cozida",
        "Linguiça calabresa",
        "Couve fatiada",
        "Caldo de legumes",
        "Azeite",
        "Cebola e alho",
        "Sal e temperos"
      ],
      "ingredientes": [
        {
          "nome": "Batata cozida",
          "quantidade_g": 190
        },
        {
          "nome": "Linguiça calabresa",
          "quantidade_g": 55
        },
        {
          "nome": "Couve fatiada",
          "quantidade_g": 45
        },
        {
          "nome": "Caldo de legumes",
          "quantidade_g": 50
        },
        {
          "nome": "Azeite",
          "quantidade_g": 8
        },
        {
          "nome": "Cebola e alho",
          "quantidade_g": 18
        },
        {
          "nome": "Sal e temperos",
          "quantidade_g": 4
        }
      ]
    },
    {
      "id": "panqueca_de_carne_com_molho_e_arroz",
      "nome": "Panqueca de Carne com Molho e Arroz",
      "categoria": "Pratos feitos brasileiros",
      "subcategoria": "Prato executivo / Restaurante",
      "porcao_referencia": "430g",
      "nutrientes": {
        "energia_kcal": 690,
        "energia_kj": 2887,
        "carboidratos_g": 72,
        "proteinas_g": 34,
        "gorduras_totais_g": 30,
        "gorduras_saturadas_g": 10,
        "gorduras_trans_g": 0.4,
        "fibra_alimentar_g": 5,
        "acucares_totais_g": 7,
        "sodio_mg": 1020,
        "colesterol_mg": null,
        "alcool_g": 0,
        "calcio_mg": 220,
        "ferro_mg": 4.2,
        "potassio_mg": 720,
        "vitamina_c_mg": 12,
        "vitamina_A_mcg": 120,
        "vitamina_D_mcg": 0.5,
        "vitamina_E_mg": 2,
        "vitamina_B12_mcg": 2.4,
        "folato_mcg": 90,
        "fosforo_mg": 430,
        "magnesio_mg": 70,
        "zinco_mg": 5,
        "selenio_mcg": 20,
        "manganes_mg": 1,
        "cobre_mg": 0.35
      },
      "fonte": "Baseado em tabelas TACO (UNICAMP), IBGE e literatura nutricional brasileira",
      "observacoes": "Panquecas recheadas com carne moída, molho de tomate e queijo, servidas com arroz branco.",
      "tags": [
        "prato feito",
        "preparação brasileira",
        "Prato executivo / Restaurante",
        "panqueca",
        "carne moída",
        "molho de tomate",
        "executivo",
        "Massa de panqueca",
        "Carne moída refogada",
        "Molho de tomate",
        "Queijo ralado ou mussarela",
        "Arroz branco cozido",
        "Óleo",
        "Sal e temperos"
      ],
      "ingredientes": [
        {
          "nome": "Massa de panqueca",
          "quantidade_g": 120
        },
        {
          "nome": "Carne moída refogada",
          "quantidade_g": 130
        },
        {
          "nome": "Molho de tomate",
          "quantidade_g": 90
        },
        {
          "nome": "Queijo ralado ou mussarela",
          "quantidade_g": 30
        },
        {
          "nome": "Arroz branco cozido",
          "quantidade_g": 120
        },
        {
          "nome": "Óleo",
          "quantidade_g": 8
        },
        {
          "nome": "Sal e temperos",
          "quantidade_g": 5
        }
      ]
    },
    {
      "id": "omelete_recheado_com_arroz_feijao_e_saladas",
      "nome": "Omelete Recheado com Arroz, Feijão e Saladas",
      "categoria": "Pratos feitos brasileiros",
      "subcategoria": "Prato executivo / Restaurante",
      "porcao_referencia": "420g",
      "nutrientes": {
        "energia_kcal": 620,
        "energia_kj": 2594.1,
        "carboidratos_g": 56,
        "proteinas_g": 33,
        "gorduras_totais_g": 29,
        "gorduras_saturadas_g": 10,
        "gorduras_trans_g": 0.3,
        "fibra_alimentar_g": 8,
        "acucares_totais_g": 4,
        "sodio_mg": 1180,
        "colesterol_mg": null,
        "alcool_g": 0,
        "calcio_mg": 260,
        "ferro_mg": 4,
        "potassio_mg": 760,
        "vitamina_c_mg": 16,
        "vitamina_A_mcg": 280,
        "vitamina_D_mcg": 2.2,
        "vitamina_E_mg": 2.8,
        "vitamina_B12_mcg": 2.1,
        "folato_mcg": 155,
        "fosforo_mg": 470,
        "magnesio_mg": 85,
        "zinco_mg": 3.6,
        "selenio_mcg": 20,
        "manganes_mg": 1.1,
        "cobre_mg": 0.35
      },
      "fonte": "Baseado em tabelas TACO (UNICAMP), IBGE e literatura nutricional brasileira",
      "observacoes": "Omelete de restaurante com queijo e presunto, servido com arroz, feijão e salada simples.",
      "tags": [
        "prato feito",
        "preparação brasileira",
        "Prato executivo / Restaurante",
        "omelete",
        "ovo",
        "executivo",
        "arroz e feijão",
        "Ovos",
        "Queijo mussarela",
        "Presunto",
        "Arroz branco cozido",
        "Feijão carioca cozido",
        "Salada simples",
        "Óleo",
        "Sal e temperos"
      ],
      "ingredientes": [
        {
          "nome": "Ovos",
          "quantidade_g": 110
        },
        {
          "nome": "Queijo mussarela",
          "quantidade_g": 35
        },
        {
          "nome": "Presunto",
          "quantidade_g": 30
        },
        {
          "nome": "Arroz branco cozido",
          "quantidade_g": 120
        },
        {
          "nome": "Feijão carioca cozido",
          "quantidade_g": 100
        },
        {
          "nome": "Salada simples",
          "quantidade_g": 60
        },
        {
          "nome": "Óleo",
          "quantidade_g": 8
        },
        {
          "nome": "Sal e temperos",
          "quantidade_g": 4
        }
      ]
    }
  ]
}
